Workbook

Sheet 文章清单
A1: 发布时间区间：2026-03-16 00:00:00~2026-03-22 23:59:59
A2: 序号 | B2: 文章分类 | C2: 公众号名称 | D2: 文章标题 | E2: 文章超链接地址 | F2: 文章发布时间 | G2: 文章文字全文内容
A3: 0001 | B3: 技术与产品创新|维保 | C3: 上海市联合电梯安全技术促进中心 | D3: 《人工智能在电梯行业的影响》--《电梯世界》2025年3月刊 | E3: http://mp.weixin.qq.com/s?__biz=Mzg3NzAzNjQ4NQ==&mid=2247514820&idx=1&sn=d68ec3acb1a5457d49a3ac041e8921c8 | F3: 2026-03-17 16:50:43 | G3: 作者：潘卡杰·普拉萨德 来源：翻译自《电梯世界》杂志官网 该论文于2024年在巴哈马天堂岛举行的国际电梯与自动扶梯研讨会上发表。1. 摘要 人工智能（AI）是一项具有变革性的新型技术，在电梯行业中有许多应用。本文将深入探讨它是什么、不是什么，以及它如何应用于你的业务，探讨其具体应用场景。 以下是一些例子： 增加新员工 缩短解决时间 优化劳动力成本 保存机构知识 本文将重点介绍具体的例子（而非技术细节），这些实例可以立即应用于您的业务。2. 引言 人工智能正在通过提供提升效率、降低运营成本和改善服务交付的解决方案，重塑行业。在电梯行业，技术技术人员对维护、修理和客户服务至关重要，AI的作用不是替代工人，而是增强他们的能力，使工作更轻松、更快速、更有信息。本文认为，人工智能可以成为弥补日益扩大的技能差距的宝贵工具，尤其是在银海啸——随着大量劳动力接近职业生涯末期、新技术人员逐渐适应，预计将迎来的退休浪潮。 人工智能可以通过解决多重挑战来支持行业，包括：增加新员工： AI辅助培训系统通过提供个性化、按需的学习体验，缩短入职时间。提供及时培训，帮助技术人员解决日益复杂系统的问题。缩短解决时间： 人工智能可以通过提供相关问题和建议解决方案，帮助技术人员识别问题，从而更快解决问题。在正确的时间提供正确的信息，有助于增强安全文化，确保技术人员依赖数据驱动的洞察，而非反复试验。更好地利用现有资源： 人工智能通过智能安排技术人员的知识/技能/经验水平，确保资源高效分配，帮助企业最大化员工的价值。保存机构知识： 随着员工快速老龄化，人工智能系统能够记录并保留高级技术人员的知识，使新员工能够多年使用。 这些人工智能应用并未减少对人类劳动力的需求;相反，它们让技术人员——无论是新手还是有经验的人——都能更聪明地工作。通过降低进入门槛，人工智能为个人进入电梯行业创造更多机会，有助于抵消退休带来的劳动力萎缩。在银海啸的背景下，人工智能提供了一种保存关键机构知识的方式，同时使这一职业对年轻一代更具吸引力。 本文将探讨电梯行业中的这些人工智能应用场景，展示这项技术不是为了取代工作岗位，而是为了提升工作，使该职业对未来从业者更具可及性、可持续性和吸引力。3. 理解电梯中的人工智能3.1 什么是人工智能 AI在电梯行业的潜力在于通过为技术人员提供实时、相关的信息，提升决策能力。通过即时访问以往案例、工作订单或快速调取服务历史，技术人员能更好地做出未来决策。 例如，当技术人员遇到陌生问题时，AI可以根据电梯工单中的类似案例提供建议，帮助更快解决问题。 此外，人工智能可以追踪性能趋势，并建议预防性维护的最佳时机，从而降低故障的可能性。通过确保正确信息在正确的时间传递，AI还通过减少技术人员在维修过程中依赖猜测或反复试验的可能性，提升了安全性。3.2 人工智能不是什么 人工智能不能替代技术人员或其他技术工人。关于人工智能的许多讨论往往倾向于更光鲜亮丽的方面，比如完全自主系统和预测性维护。但这些能力虽然引人入胜，只是其中一部分。目前的人工智能是一种辅助性技术，旨在帮助人类劳动力，而非取代他们。复杂的维修和细致入微的问题解决仍然需要只有经验丰富的技术人员才能提供的亲身操作经验。 此外，人工智能并非灵丹妙药。它需要高质量的数据才能有效，且无法在没有人工监督的情况下作为独立运营者运作。行业不应想象人工智能接管工作，而应关注如何提升现有员工的技能和能力。4. 核心论点：用人工智能增强智能4.1 快速且准确的信息检索 AI 人工智能在电梯行业应发挥的核心作用，是帮助技术人员快速获取准确信息。在停机成本高且排查耗时的领域，获取正确的数据可以带来决定性的变化。基于人工智能的平台可以实时获取过去的维护日志、手册和传感器数据，使技术人员能够更快、更有信心地解决问题。这种实时获取信息不仅提升了效率，还通过确保技术人员拥有做出明智决策所需的数据，而非依赖反复试验，强化了安全文化。 例如，当技术人员响应维修请求时，AI系统可以根据类似案例提供潜在原因列表，并附带逐步指南或视频，展示如何解决问题。这不仅节省时间，减轻技术人员的压力，还提升了客户的服务质量。它还能通过防止技术人员在不确定问题时尝试潜在修复方案，从而增强安全性。4.2 人工智能作为工具，而非替代品 需要强调的是，人工智能不会取代电梯行业中的人工元素。人工智能擅长处理重复性任务、数据分析和模式识别，但缺乏适应复杂且常常不可预测的实地工作的能力。技术人员带来了AI无法复制的必要经验、直觉和动手技能。 相反，人工智能作为一种工具，使技术人员更高效。这减轻了他们寻找信息或记忆过往维修细节的重担，使他们能够专注于工作的关键环节。通过这样做，人工智能提升了人类能力，使经验较少的工人更容易应对具有挑战性的任务，同时使经验丰富的技术人员能够更高效、更安全地工作。5. 人工智能在电梯行业的应用5.1 新员工的增加 随着大量劳动力临近退休，行业面临的最大挑战之一是快速有效地培训新员工。人工智能可以通过提供适应性、实时的训练工具，满足每个人的学习节奏，加速这一过程。AI机器人可以为新员工提供一个提出“愚蠢”问题的地方，这些问题他们平时可能不会问。 此外，这些工具还能提供即时反馈，帮助学员纠正错误并建立信心。这种方法不仅缩短了招募新员工所需的时间，还通过使培训更具互动性和个性化，提升了培训质量。实时信息的可用性确保即使是新员工也能安全工作，AI引导他们完成复杂流程，防止错误。5.2 缩短解决时间 在服务行业，解决时间是一个关键的绩效指标。AI系统可以通过根据传感器数据和过去维修情况提供建议，简化故障排查以及其他地方遇到的类似问题。这使技术人员能够更快解决问题，减少电梯停机时间，提升客户满意度。 例如，技术人员无需花费数小时诊断问题，而是将症状输入AI系统，AI系统会分析多个来源的数据，推断最可能的原因。这使技术人员能够在不必要拖延的情况下解决问题，从而腾出更多时间处理更多服务请求。通过在正确的时间提供正确的信息，人工智能帮助确保技术人员以清晰的态度处理每个问题，降低错误风险，营造安全文化。5.3 更好地利用现有资源 人工智能可以帮助企业更好地利用现有资源，根据技能、地点和工作复杂度智能安排和派遣技术人员。这确保了合适的技术人员被分配到合适的工作岗位，减少出行时间，最大化一天内完成的服务呼叫数量。 例如，人工智能可以分析公司的历史服务呼叫数据，预测高峰时段，帮助管理层相应规划人员配置。他们关注的不是降低劳动力成本，而是改善现有资源的利用方式，以更高效地满足客户需求，同时不给员工带来过重负担。此外，通过确保技术人员在需要时获得所需信息，人工智能促进安全，防止技术人员在缺乏适当背景信息时“即兴发挥”。5.4 保护机构知识 老龄化的劳动力，也被称为“银色海啸”，对电梯维护公司等行业构成重大挑战，这些行业数十年的经验和知识随着高级员工退休而面临流失的风险。人工智能可以通过捕捉和组织这些制度知识，以方便未来世代员工访问的方式来帮助保存这些机构知识。 例如，人工智能系统可以记录高级技术人员的故障排查流程、维修策略及其他见解，创建知识库，方便经验较少的员工在需要时访问。这确保了劳动力的集体智慧不会在人口结构变化时丧失。提供即时获取这些知识，使新员工能够更安全、更自信地工作，因为他们知道有经验丰富的专家指导。6. 实施人工智能的挑战与注意事项 尽管人工智能的应用潜力巨大，但也存在挑战。数据质量和可用性对于人工智能系统有效运行至关重要。如果输入系统的数据不完整或不准确，AI的建议可能存在缺陷。 变革管理也是另一个重要的考虑因素。如果技术人员担心这些系统会削弱他们的专业能力或威胁到他们的工作，可能会抵制采用这些工具。清晰的沟通和培训将是必要的，以表明人工智能是支持而非取代他们的角色的。 最后，实施人工智能工具和平台的成本可能相当可观，尤其是对小型企业而言。企业必须认真评估人工智能的长期效益与其前期成本，确保采用符合自身具体需求和能力的解决方案。7. 结论 人工智能有潜力通过增强员工的智能，而非取代它，从而改变电梯行业。面对银海啸，AI能够保存关键的机构知识，帮助更快地招聘新员工，并通过快速且准确的信息检索提升整体效率。通过聚焦人工智能如何支持技术人员的日常工作，行业不仅能保持竞争力，还能为新员工创造更多机会。 通过在正确的时间提供正确的信息，人工智能还增强了安全文化，减少了技术人员因信息不完整而犯错的可能性。随着人工智能的不断发展，它在电梯行业中的作用将不再是抢夺工作，而是赋予劳动力他们在快速变化环境中取得成功所需的工具。
A4: 0002 | B4: 事故与安全 | C4: 上海智慧电梯 | D4: 【工作动态】监管守底线_服务开新局_以实干担当保障特种设备安全运行 | E4: http://mp.weixin.qq.com/s?__biz=MzU5MTg0NTAzNw==&mid=2247509800&idx=1&sn=23a5ac0c24a8ec6d7beed427dc2d3785 | F4: 2026-03-19 16:02:12 | G4: 近期，宝山区市场监管局立足市场监管职责，坚持监管与服务并重、规范与赋能同步，在辖区开展自动扶梯安全大宣传大排查大整治工作，保障居民乘梯安全。 1 精准发力，全面整治问题隐患 认真贯彻落实区委、区政府相关部署要求，对全区范围内的在用自动扶梯开展专项排查整治，制定落实专项工作方案，以公众聚集场所使用的、投入使用年限长的、投诉举报较多的、以及近两年被列入本市电梯维保质量与信用评价“黑名单”企业维保的自动扶梯为重点，深入排查消除安全隐患，督促特种设备使用单位、维保单位落实主体责任。已出动执法人员72人次，检查单位36家、设备52台，发现并整改问题4条。 2 层层发动，加大安全宣传力度 联合区机管局等部门以及各街镇，通过张贴安全宣传海报、组织安全小讲堂、投屏滚动播放宣传片、发放安全宣传册等方式，推动电梯安全宣传进商业综合体、进医院、进学校、进社区、进企业，不断增强群众安全乘梯意识。目前，已覆盖学校286所、大型商业综合体16家、医院8家、小区210余个、工业园区2个，发放宣传册2600余本。 下一步，宝山区市场监管局将常态化开展特种设备安全监管与服务指导，完善全周期安全管控体系，并持续组织特种设备安全宣传，营造特种设备安全社会共治氛围，为宝山“一地三区”建设作出市场监管新贡献。 信息来源：宝山市场监管公众号
A5: 0003 | B5: 曳引机|技术与产品创新 | C5: 上海智慧电梯 | D5: 电梯藏在哪？这项“隐形”技术正在重塑城市天际线 | E5: http://mp.weixin.qq.com/s?__biz=MzU5MTg0NTAzNw==&mid=2247509800&idx=6&sn=9b3bb4821a0c5281281eaee78a5a0f9a | F5: 2026-03-19 16:02:12 | G5: 当你每天穿梭于高楼大厦，可曾想过，那个承载你上上下下的金属方盒，它的“心脏”究竟藏在哪里？ 传统电梯的“机房”像一顶帽子，戴在建筑的顶端，占据着本该属于视野与阳光的黄金空间。一项技术，却让这顶“帽子”彻底消失了。 它不是魔术，而是紧凑式无机房电梯曳引系统带来的空间革命。 向上而生，却不再“高高在上” 想象一下：将整台电梯的动力核心——曳引机、导向轮、承重结构——压缩、融合、集成于一个紧凑的金属框架中。这不是简单的物理叠加，而是深度的结构重构。 这一体化机架设计的精妙之处在于：它既承载着向上的力量，又在每一处折角与焊缝中诉说着精密与可靠。 当传统建筑还在为机房牺牲顶层空间时，这种集成化设计已悄然将空间归还给建筑师与业主。更多的设计可能，更高的空间利用率，让每一平方米都创造价值。 平稳的秘密：底托式轿架系统 你是否经历过电梯里人群分布不均时的轻微晃动？底托式无机房电梯轿架系统用一套精妙的力学设计给出了答案： 并排的两组轿底轮，像一双稳稳托举的手，无论轿厢内乘客如何分布，都能保持轿底的绝对平稳。四长四短的拉杆组合，牢牢拉住轿厢托支架的四个角落，如同四根有力的手指，将任何偏载倾向扼杀在萌芽状态。 而八个轿底减震垫，则是为极致体验而生的点睛之笔。 轿架是电梯的“脊梁”，支撑着城市向上的每一步。 可调节钣金导轨支架 在电梯的世界里，精度决定品质。 可调节钣金导轨支架的诞生，解决了一个长期存在的工程难题——如何应对变化的井道距离？高强度轻量化钣金通过折弯成型，借助紧固件实现精准定位与快速装配，布局紧凑却不失刚度。 它像一位精于空间规划的设计师，在保障导轨垂直度与刚度的同时，将井道空间占用率降至最低。 高强度钣金支架，为导轨提供刚性基础，为安全保驾护航。 平衡之道：集成式对重系统 电梯上行下走，背后是一场能量博弈。 集成式对重框架与曳引轮组的默契配合，通过优化配重分布与导向结构，实现了电梯运行时的载荷平衡与动态平顺性。曳引机负载减轻了，能耗降低了，系统整体能效与使用寿命却提升了。 这是一场看不见的节能革命，藏在每一次平稳的启停之中。 4：1曳引比：小比例里的大智慧 电梯曳引比4：1——这个看似专业的技术参数，实则是整个系统设计的精髓所在。 简单来说，曳引轮每转动四圈，轿厢才移动一圈的距离。这种绕绳方式带来的优势，远超常人想象： 其一，大幅降低曳引机负载与选型成本。 在4：1曳引比下，曳引机输出扭矩理论上仅为1：1绕法的四分之一。相同载重与速度条件下，可选用功率和扭矩更小的曳引机——电机体积、重量及成本显著下降，驱动系统配置也更加经济。 其二，提升运行平稳性与乘坐舒适度。 曳引轮的高速转动被转化为轿厢的低速平移，如同给电机运转带来的振动与冲击加上了一道缓冲。多组滑轮使钢丝绳张力分布更均匀，单根绳受力减小，磨损更加均衡——运行时噪声与抖动，就这样被层层化解。 其三，延长钢丝绳等核心部件的使用寿命。 单根钢丝绳受力仅为1：1绕法的四分之一，疲劳损伤大幅减轻，更换周期得以延长。这不仅降低了维护成本，更提升了全生命周期的经济性。 其四，具备明显的节能优势。 曳引机长时间运行在低扭矩工况下，电机效率更高，整体能耗低于传统绕法。低扭矩输出同时使制动器负荷减小，制动响应更精准，制动能量消耗同步降低。 其五，更适应无机房及小井道建筑需求。 小体积曳引机可灵活集成于机架、轿顶或对重架上，无需独立机房——这一优势在现代紧凑型建筑及旧楼加装电梯场景中尤为突出。滑轮布局灵活多变，在有限空间中实现大载重与高速度，让井道利用率大幅提升。 写在最后 城市在向上生长，而支撑这种生长的技术，却在悄然“隐形”。 当我们不再被传统机房的束缚所限，建筑的天际线便有了更多可能。紧凑式无机房电梯曳引系统，不只是技术的进步，更是对城市空间价值的重新思考。 每一次平稳的上升，每一次安静的停靠，都在诉说着一个事实： 真正的创新，往往藏在看不见的地方。 而你每天乘坐的那部电梯，或许正是这项“隐形”技术的最佳代言人。 信息来源：半盏清谈话春秋公众号
A6: 0004 | B6: 政策与法规|设计 | C6: 上海智慧电梯 | D6: 消防电梯规范速记：哪些建筑要设？基本要求是什么？ | E6: http://mp.weixin.qq.com/s?__biz=MzU5MTg0NTAzNw==&mid=2247509800&idx=5&sn=349b3ac9bd522fbfc7dff1064ff33ed8 | F6: 2026-03-19 16:02:12 | G6: 消防电梯 是建筑物发生火灾时 供消防人员进行灭火与救援使用的特殊电梯 在火灾中扮演着至关重要的角色 那么，它需要满足哪些要求呢？ 今天就为大家系统梳理一下 哪些建筑必须设置消防电梯？ 01 例外情况 城市综合管廊、交通隧道，以及室内无车道且无人员停留的机械式汽车库可不设置。 轨道交通工程中的埋地部分也可不设置。 小结：消防电梯的设置核心是为人员安全服务，主要针对建筑体量大、高度高、人员密集或情况特殊的场所。 消防电梯有哪些基本要求？ 02 小结：消防电梯在设计中兼顾常态与应急状态，既要保证日常使用的便捷，更要确保在火灾发生时能成为一条安全、可靠的快速通道。 消防电梯是建筑消防安全体系中不可或缺的一环，其规范设置与合格设计，直接关系到火灾救援的效率与人员生命安全。 信息来源：四川特种设备公众号
A7: 0005 | B7: 技术与产品创新|事故与安全 | C7: 上海智慧电梯 | D7: 如何更安全地为电梯门“体检”：远程操控的摆锤测试新装备 | E7: http://mp.weixin.qq.com/s?__biz=MzU5MTg0NTAzNw==&mid=2247509800&idx=7&sn=98d61a7cfa9cf744bef8ae90d2430f2d | F7: 2026-03-19 16:02:12 | G7: 电梯门的坚固程度直接关系到乘客安全。为了检验它的抗冲击能力，工程师们需要进行一项重要的测试——用沉重的摆锤撞击电梯门。 但传统的测试方法存在隐患：操作员需要手动释放高悬的摆锤，在摆锤撞击门板反弹时，有被误伤的风险。 为此，一项新的安全装置应运而生。它就像一个可由地面远程控制的“机械爪”，让操作员能够安全、精准地完成摆锤的抓取与释放，彻底将测试人员与危险区域隔离。一、 核心原理：远程牵线，操控“机械手”这个装置的核心是一个巧妙的夹持机构，它由两个对称的“机械爪”组成。测试人员无需靠近摆锤，只需在地面拉动不同的绳子，就能通过一套连杆系统，远程控制“机械爪”的开合。1. 夹持（抓牢摆锤）： ⑴当需要抓取悬吊摆锤的钢丝绳时，测试人员拉动夹持牵引绳。 ⑵这根绳子会拉动一组呈“倒V字”形的上连杆，使它们的夹角变小。 ⑶上连杆的运动，会驱动两个“机械爪”像剪刀一样合拢，从而稳稳夹住摆锤的吊绳。 2. 释放（进行撞击）： ⑴当一切准备就绪，需要释放摆锤进行撞击测试时，测试人员拉动另一根释放牵引绳。 ⑵这根绳子会拉动另一组“倒V字”形的下连杆。 ⑶下连杆的运动，会迫使“机械爪”的根部互相靠近，从而像张开手掌一样让爪子的前端打开，释放摆锤。 简单比方：可以把它想象成一个用两根线控制的、放大了的简易机械手或抓取器。拉A线，手就握紧；拉B线，手就松开，而测试人员可以始终站在安全距离之外。二、 它如何用于实际测试？整个测试过程安全且有序：1. 准备：将摆锤通过钢丝绳吊至规定高度。 2. 抓取：将吊着摆锤的钢丝绳放入张开的“机械爪”口中，然后在地面拉动夹持牵引绳，“机械爪”牢牢闭合，将摆锤的拉到需要的角度和高度。 3. 释放与撞击：所有人员撤离到安全区域后，测试人员在地面拉动释放牵引绳。“机械爪”瞬间张开，摆锤如钟摆般自由落下，精确地撞击到要测试的电梯门板上。 4. 分析：工程师通过传感器记录电梯门板变形数据，评估电梯门的抗冲击性能。三、 优势1. 保护人员安全：最大亮点在于实现了人员与危险区域的物理隔离。测试人员全程在地面安全位置作业，彻底避免了被反弹摆锤撞击的风险。 2. 操作精准可靠：通过机械连杆传动，动作明确，夹持与释放状态清晰，避免了人工操作的不稳定性。 3. 结构简单耐用：装置主要由连杆、销轴和钢丝绳构成，制造成本极低、结构坚固、不易损坏、维护方便，适合在测试装备里反复使用。 4. 提升测试效率：标准化的远程操作流程，减少了每次测试前的安全准备时间，使得测试工作更快捷、更规范。写在最后这个电梯摆锤夹持及释放装置，虽是一个专注于测试环节的改进，却体现了“安全第一”的工程智慧。它将高风险的人工操作，转化为稳定可靠的远程机械控制，不仅保护了测试人员的安全，也提升了测试可靠性。 信息来源：半盏清谈话春秋公众号
A8: 0006 | B8: 事故与安全 | C8: 上海智慧电梯 | D8: 3·15安全提示丨进出电梯时，多留意这5件事 | E8: http://mp.weixin.qq.com/s?__biz=MzU5MTg0NTAzNw==&mid=2247509800&idx=3&sn=1adb91dde5809ef012644914c399789a | F8: 2026-03-19 16:02:12 | G8: 、 3.15关注 电梯安全 ELEVATOR 电梯，是人们出行的“刚需” 但你知道吗？ 电梯关门的那一瞬间 也需要注意安全！ 痛心案例 2020年5月，湖北大冶某小区发生惊险一幕，一名两岁女童的遭遇，让所有家长揪心。 据媒体报道，事故当天，妈妈带着女童准备乘电梯下楼，为了防止孩子乱跑，妈妈使用透明安全牵引绳牵住女童。女童先行跑进电梯轿厢，妈妈则还站在门外整理物品且未松开牵引绳。电梯门关闭后，牵引绳被夹在门缝中，未被电梯光幕检测到。电梯上行时，女童瞬间被牵引绳拽住，吊离轿厢地面，悬挂在电梯门上。监控显示，女童悬空后吓得大哭不止，双手拼命抓挠却根本够不到轿厢。万幸的是，电梯运行中触发了急停装置，悬停在楼层之间。物业和维保人员紧急赶到，将女童救下。事后检查，女童仅受惊吓和轻微擦伤，并无大碍。但这惊魂一幕，足以让家长后怕终生。 同类事故频发无独有偶，2022年7月，广东佛山一名女子牵狗乘坐电梯时，狗狗先进入轿厢，女子和狗绳还留在门外。电梯门关闭时未识别到纤细的狗绳，启动上行后，女子被狗绳猛地拽起，狠狠撞向电梯门框顶部，当场倒地受伤。 电梯的“检测盲区” 电梯的光幕看似灵敏，其实也有检测盲区。在正常使用的情况下，它只能感应、识别到从轿厢地面往上大约2.5厘米到1.6米范围内的物体，以及直径超过5厘米（比如成年人拳头大小）的障碍物。 小孩的手指、老人的拐杖、购物袋的提手等都可能成为“漏网之鱼”。 更要当心的是，当电梯门关闭到只剩最后2厘米（约一根成人手指的宽度）的缝隙时，部分保护装置的功能会自动取消，此时若强行扒门、抢进抢出，极易被门牢牢夹住。 此外，像“郑州事故”中的老旧电梯，因零部件磨损、维保缺失，光幕灵敏度会大幅下降，门机力矩也会出现异常。可能出现 “该停不停、该开不开” 的故障，进一步放大安全风险。 这3个误区，你知道吗？ ❌ 电梯门能自动感应，不会夹人？ ✅ 光幕有盲区，细小的物体可能检测不到。拐杖、裙摆、狗绳都要留意。 ❌ 电梯故障时，扒门逃生最快？ ✅ 强行扒门极易坠落井道，正确做法是按紧急按钮并拨打求救电话，安静等待救援。 ❌ 检验时间超期而已，电梯还能用？ ✅ 检验时间超期意味着未通过定期检验，属于违法使用，隐患极大。看见过期，就要投诉。 正确乘梯，牢记这5条 01. 候梯时，绝不倚靠层门 等待电梯时，不要将手、脚、身体倚靠在电梯门上。确认轿厢到达且完全停稳后，再有序进出。 02. 进出时，千万别抢行 电梯门即将关闭时，不要冲刺抢进。若被门轻轻夹住，多数电梯会自动弹开，此时切勿慌张拉扯；若门未弹开，立即按开门键或大声呼救。 03. 携带物品时，务必多留意 携带行李、婴儿车、购物车时，确保物品完全进入轿厢再按关门键。避免细小部件卡在门缝里，引发门体故障。老人、小孩乘梯，最好有人陪同看护。 04. 遇电梯故障时，坚决不扒门 若电梯门无法正常开关或轿厢突发停运，绝对不能强行扒门逃生！立刻按下轿厢内的紧急报警按钮，等待专业救援。保持冷静，切勿在轿厢内蹦跳、喧哗。 05. 发现异常，及时反映 若遇到电梯门异常开关、运行异响、急停急坠等情况，一定要及时向物业或电梯维保单位反映，切勿心存侥幸继续使用。 消费者专属 3.15维权实操指南 电梯安全不是“等别人管” 而是“我们可以管” 第一步：学会看“两样东西” 进电梯先看这两处： 《特种设备使用标志》——看“下次检验日期”是否过期； 《维保公示卡》——看最近一次维保时间是否在十五天内；若标志过期、缺失或模糊不清，拍照留存。 第二步：发现问题怎么反映？ 向物业书面反映（建议通过业主群接龙或书面联名，留存证据）； 要求物业提供最近一次维保记录——业主有权查阅。 第三步：投诉渠道 拨打12345或12315（市场监管部门）； 投诉内容模板：“XX小区X栋电梯，检验时间超期/维保标志已过期/无维保记录，存在安全隐患，请核查。”； 通过“全国12315平台”微信小程序上传照片投诉，更方便快捷。 信息来源：中国电梯公众号
A9: 0007 | B9: 事故与安全 | C9: 上海智慧电梯 | D9: 转扩！这个紧急“救命钮”，你一定要知道 | E9: http://mp.weixin.qq.com/s?__biz=MzU5MTg0NTAzNw==&mid=2247509800&idx=4&sn=fc20fff4efc573e1f1c7caa5ed674502 | F9: 2026-03-19 16:02:12 | G9: 乘坐扶梯时 看到有人摔倒、被卡 或扶梯突然发出异响、颤动时 你知道该怎么办吗？ 手掌被卡进扶梯缝隙 1月18日，广西南宁市西乡塘区一商场内，一名8岁女孩被卡在扶梯内。消防员到场后发现小女孩的右手手掌露出部分已发生变形。 消防员立即利用多种工具对扶梯的金属护板进行拆卸，约5分钟后女孩成功脱困，现场医护人员立即将其送医。 图源：广西消防 乘梯失衡头朝下摔倒 近日，在北京地铁大屯路东站，两名女子携手乘坐自动扶梯时突然失衡后仰，瞬间头朝下随滚梯倒滑。 千钧一发之际，公交警方巡逻民警扑向急停按钮迅速制动扶梯，将两人安全救下，所幸无大碍。 图源：平安北京 扶梯遇险怎么办？ 记住一个“救命钮” 按：紧急制动按钮 紧急制动按钮通常设在手扶电梯的两端，常位于踏板附近、扶手侧下方等处，部分长距离扶梯也会在中段设置，通常为一个红色（偶见黄色）的圆形按钮。 图源：国家应急科普宣传 呼：遇险大声呼救 如果衣物、鞋、裙子等物品被夹要大声呼救，让靠近紧急按钮处的人按下紧急按钮，扶梯会缓冲几十厘米后自动停下。 如果无法第一时间按下停止按钮，大声呼救的同时，紧紧抓住扶手，抬起脚，这样人就会随着扶梯的护栏移动，以免摔倒。 护：摔倒保护头部 一旦摔倒，应尽量蜷成球状，双手交叉放在颈部、后脑部，双臂护住太阳穴，以防叠压对自己造成致命伤害。 自动扶梯的“咬人”区域 除了掌握扶梯事故的紧急应对措施，日常生活中乘坐扶梯也要避开以下位置，防止被“咬”。 梳齿板 梳齿板是自动扶梯的重要安全装置，可避免梯级上的异物卷入扶梯内部，但一定要小心梳齿板接合处的缝隙。切勿让手、脚、衣服下摆等靠近该缝隙，以防发生夹卷事故。 围裙板 搭乘扶梯时，你是否留意过脚边两侧的“毛刷”？它们可不是用来刷鞋的！ 它是“围裙板防夹装置”，又称“裙板刷”，其主要作用是防止夹人夹物事故的发生。如果不慎碰到，请注意远离。 三角区域 一些商场内的扶梯和建筑物会形成一个锐角三角形空间，该区域极易卡住儿童的脖子或手臂。家长带孩子乘坐扶梯时，应让儿童站在内侧以远离危险。 转扩！乘扶梯“五注意” 不要倚靠扶梯侧面围裙板； 不要让手、脚、衣服下摆等靠近扶梯夹缝，避免发生夹卷事故； 不要在梯级上快步走动、奔跑、攀爬，更不能逆行； 不要将身体探出扶手装置以外，以防碰撞或坠落； 不要将尖利硬物插入扶梯缝隙或凹槽处； 不要停在扶梯出口，以防跟后方人员发生碰撞。 提醒大家 搭乘扶梯时应留意脚下 站立在梯级黄线区域以内 家长监管好孩子 乘梯时勿奔跑、打闹 看到有人摔倒、被卡 应及时按下紧急制动按钮 谨慎乘梯 安全第一 信息来源：中国电梯公众号
A10: 0008 | B10: 设计 | C10: 上海电梯 | D10: 达奥斯___以装潢为笔，用匠心绘就“好电梯”图景 | E10: http://mp.weixin.qq.com/s?__biz=MzA4MTUwOTExOA==&mid=2650808865&idx=1&sn=649ca1babc8cc1a486bd024d694b702a | F10: 2026-03-16 10:23:40 | G10: 你眼里的电梯，是什么样子？是冰冷的金属厢体，还是匆匆路过的过渡空间？在达奥斯，我们始终坚信，电梯不该只满足“能运行”的基础标准，更应成为承载温暖、适配需求的人文空间——这是达奥斯深耕电梯装潢领域以来，从未动摇的核心理念。 作为一家以电梯装潢为核心的企业，达奥斯的发展，始于对行业偏见的打破与对用户体验的深耕。在行业普遍将重心放在电梯运行性能、忽视装潢体验的时期，达奥斯率先聚焦“轿厢体验升级”，提出“装潢不是表面功夫，而是电梯的人文底色”的理念，将每一处装潢细节都与用户需求紧密结合。 从创业初期至今，达奥斯始终以“匠心”为尺，将“把每个轿厢当作家来装”的初心，融入企业发展的每一个环节。团队深耕楼宇、社区等各类场景，深入调研不同人群的出行需求，将设计构想转化为一个个贴合实际的实景呈现，让电梯装潢摆脱“同质化”困境，更具实用性与人文温度。 在达奥斯的理念里，电梯装潢既是轿厢的“外衣”，更是用户体验的“镜子”，每一处细节的打磨，都是对“好电梯”标准的践行。防磕碰的软包边角，守护老人与孩童的出行安全；保护视力的暖光照明，缓解长时间乘梯的视觉疲劳；适配轮椅的平整门槛装潢，兼顾特殊人群的出行便利，这些看似微小的设计，都是达奥斯对用户需求的细致回应。 深耕不辍，初心不改。如今，达奥斯始终以用户需求为导向，持续优化装潢设计与服务，将更多市民的真实出行体验融入产品研发与落地全过程。不追求刻意的华丽，不忽视细微的需求，达奥斯用专业与匠心，让每一台经过装潢的电梯，都能成为出行路上的“小温暖”，用装潢为笔，一点点绘就属于“好电梯”的美好图景，为电梯行业的人文升级注入持久力量。
A11: 0009 | B11: 国际标准与人才 | C11: 上海电梯 | D11: 技绽锋芒_匠筑未来—2025_年上海市专项职业技能大赛电梯安装维修工项目虹口区颁奖圆满落幕 | E11: http://mp.weixin.qq.com/s?__biz=MzA4MTUwOTExOA==&mid=2650808874&idx=1&sn=f13552e01c931491189543a49bdca16e | F11: 2026-03-17 12:23:25 | G11: 近日，上海市人力资源和社会保障局公布了“2025 年上海市专项职业技能大赛”获奖选手和为大赛赛事组织作出突出贡献单位。虹口区代表队荣获大赛“突出贡献单位”，上海市电梯行业协会作为“电梯安装维修工”项目技术支持单位荣获大赛“优秀组织单位”。 2026年3月17日上午，上海市电梯行业协会为虹口区6名电梯安装维修工项目获奖选手颁奖。 陈诚、汪普林荣获三等奖及晋升高级技师，由协会秘书长王俊颁奖。 李俊良、王存根、王海龙、王宏武等选手凭借扎实的专业功底与稳定发挥，荣获优胜奖，由协会首席技术专家徐国强、何新民颁奖。 最后，秘书长王俊对获奖选手们表达了诚挚的祝贺，并指出了电梯行业技能人才的重要性及电梯安装维修工对于确保电梯安全质量、市民出行安全方面不可或缺的关键作用。王秘表示：协会一直致力于行业技能人才培养，在积极推动电梯安装维修工薪资待遇题升、行业有序竞争等方面持续发力！王秘还对选手们精湛扎实的技能做了肯定，并鼓励选手们再接再厉，发扬光大，传授技能，传播正能量！ 本次大赛聚焦电梯安装维修核心技能，以赛促学、以赛促训、以赛促建，为行业技能人才搭建了切磋技艺、展示风采的重要平台。选手们在赛场上严谨操作、精益求精，用实际行动诠释新时代技能从业者的责任与担当。 下一步，协会将紧扣全市技能人才与职业技能竞赛工作部署，持续发挥技能大赛示范引领作用，深化技能人才培育，大力弘扬工匠精神，营造尊重技能、崇尚创新的社会氛围，为区域经济高质量发展注入坚实技能力量。
A12: 0010 | B12: 其他 | C12: 上海电梯 | D12: 破用工难题_解能力提升—上海电梯行业_HR_沙龙第二次活动圆满举办 | E12: http://mp.weixin.qq.com/s?__biz=MzA4MTUwOTExOA==&mid=2650808886&idx=1&sn=ffc7fd18947148d44e3edcedc000b558 | F12: 2026-03-18 15:53:13 | G12: 为破解电梯行业人力资源管理热点痛点，搭建行业HR 同仁交流互动、共促提升的专业平台，2026 年 3 月 18 日下午，由上海市电梯行业协会牵头打造的电梯行业人力资源交流互动平台（电梯行业 HR 沙龙）第二次活动在协会办公室成功举办。本次活动聚焦行业 HR 管理核心需求，汇聚 12 家行业骨干企业的 HR 负责人参会，围绕 HR 管理能力提升、安装维修工用工难、维保人员薪资调研等关键议题展开深度探讨，为电梯行业高质量发展注入人才管理新动能。 本次活动由协会首席技术专家何新民担任主持，活动伊始，主持人代表协会对各位参会同仁的莅临表示热烈欢迎和衷心感谢，并指出HR管理是企业发展的核心竞争力，尤其是在电梯行业，如何提升HR团队的专业能力、优化管理模式，直接关系到企业人才留存和发展质量。 活动特邀原上海市劳动和社会保障学会副会长叶维弘带来“HR 管理能力提升建设” 专题分享，旨在助力企业破解 HR 管理工作难题，推动行业人力资源管理提质增效。 针对当前电梯行业普遍面临的安装维修工用工难这一共性痛点，由协会杨玥老师进行了专题分享：杨老师指出该问题需企业、协会等多方发力，从改善行业生态、提升薪资待遇、提高社会地位、增强从业者技能等方面系统性解决，并重点介绍协会推出的系列举措，核心围绕电梯安装维修工培养展开，具体如下： 规范市场与定价，通过搭建零部件数据库平台、建立成本评估和公平定价引导机制，遏制低价恶性竞争，为人才培养营造良性行业环境，还推出“信得过” 维保企业认证，以技能等级工比例为核心指标，鼓励企业重视高技能人才培养。 强化宣传与公众沟通，通过新媒体宣传、开设一线员工故事栏目、筹备“好电梯” 标准市民大讨论，提升行业和维保工社会形象，增进公众理解，为人才发展营造良好社会氛围。 聚焦从业者技能提升与职业发展，明确其作为上海急需紧缺高技能人才的定位，依托政府政策补贴，全面推进职业技能培训与等级认定，常态化开展技能竞赛；重点筹备2026 年 3 月电梯安装维修工三级 / 高级工培训，明确该证书的补贴、积分落户、全国通用等优势及报名条件，同时回应企业需求，推出电梯维修上岗证（T 证）培训并明确相关报名事宜，助力企业和员工实现双赢，夯实行业人才队伍建设。 协会蒋颖老师对“信得过”维保企业认证活动进行简单介绍，阐释了 “提升维保工待遇” 的底层逻辑，为企业制定维保人员薪资体系提供了专业参考，也希望倾听HR同仁们的建议。 在随后的互动交流环节，参会同仁围绕本次活动的所有分享内容，结合自身工作中遇到的HR 管理、用工招聘、薪资制定等难点痛点，积极提问、深入交流，在思想碰撞中凝聚共识、收获经验。根据大家的发言，上海市劳动和社会保障学会副会长叶维弘支招，给大家拓展了思路。 协会未来将持续发挥电梯行业HR 沙龙的平台作用，不断聚焦行业人力资源管理的新问题、新需求，组织更多高质量的交流活动，推动行业 HR 同仁互学互鉴、共同提升，以优质的人力资源管理体系助力电梯行业高质量发展。
A13: 0011 | B13: 其他 | C13: 上海电梯 | D13: 破用工难题_解能力提升—上海电梯行业_HR_沙龙第二次活动圆满举办 | E13: http://mp.weixin.qq.com/s?__biz=MzA4MTUwOTExOA==&mid=2650808888&idx=1&sn=cdaed27d325b23185b10302b9ea9cde3 | F13: 2026-03-18 16:26:30 | G13: 为破解电梯行业人力资源管理热点痛点，搭建行业HR 同仁交流互动、共促提升的专业平台，2026 年 3 月 18 日下午，由上海市电梯行业协会牵头打造的电梯行业人力资源交流互动平台（电梯行业 HR 沙龙）第二次活动在协会办公室成功举办。本次活动聚焦行业 HR 管理核心需求，汇聚 12 家行业骨干企业的 HR 负责人参会，围绕 HR 管理能力提升、安装维修工用工难、维保人员薪资调研等关键议题展开深度探讨，为电梯行业高质量发展注入人才管理新动能。 本次活动由协会首席技术专家何新民担任主持，活动伊始，主持人代表协会对各位参会同仁的莅临表示热烈欢迎和衷心感谢，并指出HR管理是企业发展的核心竞争力，尤其是在电梯行业，如何提升HR团队的专业能力、优化管理模式，直接关系到企业人才留存和发展质量。 活动特邀上海市劳动和社会保障学会副会长叶维弘带来“HR 管理能力提升建设” 专题分享，旨在助力企业破解 HR 管理工作难题，推动行业人力资源管理提质增效。 针对当前电梯行业普遍面临的安装维修工用工难这一共性痛点，由协会杨玥老师进行了专题分享：杨老师指出该问题需企业、协会等多方发力，从改善行业生态、提升薪资待遇、提高社会地位、增强从业者技能等方面系统性解决，并重点介绍协会推出的系列举措，核心围绕电梯安装维修工培养展开，具体如下： 规范市场与定价，通过搭建零部件数据库平台、建立成本评估和公平定价引导机制，遏制低价恶性竞争，为人才培养营造良性行业环境，还推出“信得过” 维保企业认证，以技能等级工比例为核心指标，鼓励企业重视高技能人才培养。 强化宣传与公众沟通，通过新媒体宣传、开设一线员工故事栏目、筹备“好电梯” 标准市民大讨论，提升行业和维保工社会形象，增进公众理解，为人才发展营造良好社会氛围。 聚焦从业者技能提升与职业发展，明确其作为上海急需紧缺高技能人才的定位，依托政府政策补贴，全面推进职业技能培训与等级认定，常态化开展技能竞赛；重点筹备2026 年 3 月电梯安装维修工三级 / 高级工培训，明确该证书的补贴、积分落户、全国通用等优势及报名条件，同时回应企业需求，推出电梯维修上岗证（T 证）培训并明确相关报名事宜，助力企业和员工实现双赢，夯实行业人才队伍建设。 协会蒋颖老师对“信得过”维保企业认证活动进行简单介绍，阐释了 “提升维保工待遇” 的底层逻辑，为企业制定维保人员薪资体系提供了专业参考，也希望倾听HR同仁们的建议。 在随后的互动交流环节，参会同仁围绕本次活动的所有分享内容，结合自身工作中遇到的HR 管理、用工招聘、薪资制定等难点痛点，积极提问、深入交流，在思想碰撞中凝聚共识、收获经验。根据大家的发言，上海市劳动和社会保障学会副会长叶维弘支招，给大家拓展了思路。 协会未来将持续发挥电梯行业HR 沙龙的平台作用，不断聚焦行业人力资源管理的新问题、新需求，组织更多高质量的交流活动，推动行业 HR 同仁互学互鉴、共同提升，以优质的人力资源管理体系助力电梯行业高质量发展。
... A480: 0478 | B480: 政府行政令|维保 | C480: 西继迅达电梯有限公司 | D480: 解放区住建局：电梯换新颜_安居更安心 | E480: http://mp.weixin.qq.com/s?__biz=MzA4MjczNDgxMw==&mid=2649796565&idx=2&sn=3a5e9132a75567dd4bdb95c8bea1da65 | F480: 2026-03-20 10:02:42 | G480: 近日，走进解放区西城美苑、万联世纪城等小区，一台台崭新电梯平稳运行，居民出行更安全、更舒心。这是解放区扎实推进老旧电梯更新工程，把民生实事办到群众家门口的生动缩影。 采取“错峰施工、留梯通行”的工作方式 民有所呼，政有所应。老旧电梯老化、故障频发，直接关系居民出行安全和居住品质。2025年，解放区抢抓国家超长期特别国债政策机遇，将老旧住宅电梯更新作为重点民生工程加快推进，切实解决群众“急难愁盼”。全年共更新符合条件的老旧电梯157部，覆盖6个街道办事处、18个小区，惠及5162户居民，争取国债资金2355万元，用“小电梯”托起群众“大幸福”。 为把民生工程办实办好，解放区住建局主动担当、高效推进，成立工作专班，统筹协调、上下联动。通过拉网式排查建立“一梯一档”，精准摸清底数；积极争取资金支持，破解改造难题；逐户上门沟通协调，充分倾听居民诉求；公开遴选电梯品牌，全程监督施工质量，确保每个环节规范透明。施工过程中，采取“错峰施工、留梯通行”，最大限度减少对居民日常生活的影响，贴心服务赢得群众广泛认可。 新电梯运行平稳安全 截至目前，西城美苑、万联世纪城、解放教育小区等14个小区87台新电梯已投用，运行平稳安全，彻底告别故障频发、久等不来的困扰。“新电梯又稳又快，上下楼再也不发愁！”居民们的由衷点赞，正是民生工程最好的口碑。 用心用情解民忧，真抓实干惠民生。解放区将加快剩余电梯更新，强化质量监管与长效运维，持续办好群众身边“关键小事”，不断提升居民获得感、幸福感、安全感，让“住有优居”的美好愿景照进现实。 来源：“解放视窗”微信公众号 作者：张苗 闪晶 总监制：陈金平 主 编：詹长松 吕 捷 统 筹：赵亚辰 责 编：王 鹏 朱丽颖 校 审：薛 莹 编 辑：皇甫胜彬
A481: 0479 | B481: 电梯企业项目 | C481: 西继迅达电梯有限公司 | D481: 西继迅达_×_焦作美中城｜旧梯焕新_品质出行升级 | E481: http://mp.weixin.qq.com/s?__biz=MzA4MjczNDgxMw==&mid=2649796565&idx=3&sn=0193fe0c18d34b74cd85f4c12ef5bce8 | F481: 2026-03-20 10:02:42
A482: 0480 | B482: 事故与安全 | C482: 西继迅达电梯有限公司 | D482: 安全乘梯“八不要” | E482: http://mp.weixin.qq.com/s?__biz=MzA4MjczNDgxMw==&mid=2649796567&idx=1&sn=b0a1e579bf63d8da13de4a5cb4a43064 | F482: 2026-03-21 10:01:15 | G482: 随着城市化发展 电梯已经成为人们日常 必不可少的交通工具之一 遵守电梯规范 安全乘梯“八不要” 从你我做起 安全乘梯“八不要” “一不要” 电梯是公共场所，不要在里面吸烟、吐痰、乱扔杂物、乱涂乱画。 “二不要” 按电梯开关门键，轻按一次即可，不要用力拍打控制面板。 “三不要” 电梯突然停运时，不要强行扒门打开电梯，以防电梯突然启动。 “四不要” 为了您和他人的安全，不要将电动车推入电梯。 “五不要” 电梯超载报警时，不要挤入轿厢或搬入物品。 “六不要” 不要在电梯内大声喧哗、嬉戏，不要乱蹦乱跳，以免影响电梯正常运行。 “七不要” 爱护厢内设施，不要无故按动警铃按钮。禁止乱动按钮。 “八不要” 不要用伞柄、木棍、尖刀、钥匙等硬物按动或拍打显示按键。 关注我们 © 西继迅达电梯有限公司微信公众平台 订阅号：XJ Schindler 网址：www.xjschindler.com 电话：400-811-6869 点击右上角→分享给朋友或者分享到朋友圈
A483: 0481 | B483: 事故与安全 | C483: 西继迅达电梯有限公司 | D483: 电梯扶梯安全知识 | E483: http://mp.weixin.qq.com/s?__biz=MzA4MjczNDgxMw==&mid=2649796567&idx=2&sn=98344dcc8464115080cd06042f9b1dfa | F483: 2026-03-21 10:01:15 | G483: 电梯扶梯安全知识
A484: 0482 | B484: 技术与产品创新|合作与展会|广告 | C484: 赛尔电梯 | D484: 向上而生，共鉴新章｜佐上电梯2026新品发布会圆满礼成 | E484: http://mp.weixin.qq.com/s?__biz=MjM5MDU1NzI5NQ==&mid=2651538474&idx=1&sn=0b2cb990ec146f5e88b4a0442851fb14 | F484: 2026-03-16 08:08:37 | G484: 上图为广告 2026 年 3 月 10 日，佐上电梯2026年度新品发布会在宁波市奉化区溪口隆重举行。本次发布会以 “以匠心·见新生” 为核心主题，汇聚行业精英、合作伙伴及媒体代表，共同见证品牌创新成果，解码行业发展新趋势。发布会通过总经理致辞、新品揭幕、政策发布、深度交流及答谢晚宴五大环节，构建起品牌与市场的深度对话桥梁，彰显了佐上电梯深耕领域、赋能生态的坚定决心。 下午两点，嘉宾们陆续抵达活动现场，在工作人员的引导下有序签到。现场布置遵循极简高端美学，嘉宾们在签名墙前驻足留影，交流行业动态，期待着发布会的核心环节。 ·佐上电梯总经理陈永拓上台致辞 发布会伊始，佐上电梯总经理陈永拓先生发表致辞。陈总首先对莅临现场的各位嘉宾表示诚挚感谢，随后回顾了品牌在过往发展中的沉淀与突破，展现了品牌在技术研发、市场布局及客户服务等方面的核心优势。陈总表示，未来品牌将以更优质的产品与服务赋能合作伙伴，共同推动行业高质量发展。 ·佐上电梯技术总监梁玉海上台致辞 在全场期待中，发布会进入核心环节—— 新品揭幕。伴随着灯光聚焦，佐上电梯新品正式亮相。通过沉浸式演示与三维可视化呈现，新品在核心技术、产品性能、应用场景等方面的突破的得到全面解读： ·智尚系列：用创新和独特的设计结构，保证结构稳定的同时，提升轿厢空间，优化井道利用率； ·云尚系列：【入木-1】【入木-2】【革新-2】新装潢亮相； ·御尚系列：主打梯型御尚系列全面升级，空间利用率全面提高； ·悦尚系列：参数范围全面覆盖，六大全新装潢供您选择，高性价比标杆产品; ·ZS3000系列：中国上海、宁波、日本三大佐上研发中心联合设计，引进日本数十年沉淀的电梯技术和设计理念...... 新品的发布不仅展现了佐上电梯的研发实力，更满足了家用电梯各种场景的应用需要，并节省电梯的全生命周期投入，让家用电梯更智能，更节能，更安全，更美观，为行业发展注入新的活力。 ·佐上电梯销售总监郑志雄上台致辞 为助力合作伙伴抢占市场先机，发布会现场同步发布 2026 年度市场支持政策。品牌销售总监郑志雄从供货保障、渠道赋能、营销支持、培训体系四大维度，详细解读了政策核心内容：新店扶持（工厂提供免费平面设计，专卖店工厂补贴2年，样梯支持，营销费用补贴）；合作权益（十大优享，发运返利）等等，为合作伙伴构建起全方位、多层次的支持体系。该政策的发布得到了现场合作伙伴的高度认可，进一步夯实了品牌与渠道的合作根基，为市场拓展注入强劲动力。 在交流分享环节，行业专家、核心合作伙伴代表围绕 “新品应用场景拓展”“行业趋势预判”“渠道协同创新” 等议题展开深度对话。嘉宾们结合自身实践经验，分享了对新品市场前景的看好，同时就合作中的痛点、难点及解决方案交换了意见。某合作伙伴代表表示：“佐上电梯此次发布的新品在技术上实现了重大突破，配套政策也极具诚意，让我们对未来合作充满信心。” 现场思想碰撞不断，为品牌与合作伙伴的协同发展凝聚了共识、明确了路径。 一席晚宴，一份心意 一声致谢，一路同行 感恩所有支持与陪伴的 家人、朋友与伙伴 因你们相伴，方有今日成长 笑语相伴，情谊绵长 并肩同行的时光，皆为宝贵珍藏 山水一程，感恩有你 未来可期，携手共进 愿意继续同心相伴 续写不凡，共赴新程 ·佐上电梯工厂实拍图 此次新品发布会的圆满落幕，标志着佐上电梯正式开启 2026 年战略新篇章。未来，佐上电梯将以此次发布会为契机，持续深化创新驱动，强化生态协同，与所有合作伙伴携手并肩，在行业变革的浪潮中勇立潮头，共同书写共赢发展的崭新篇章。 温馨提示 如果你喜欢本文，请分享到朋友圈，想要获得更多信息，请关注我。关于今天的话题，你还有什么想法吗？欢迎留言评论，和我们一起交流哦 saierdt | 赛尔电梯 做电梯，我们更专业致力于成为具有影响力的电梯传播服务机构
A485: 0483 | B485: 企业调研与地域发展|模式创新与进展 | C485: 赛尔电梯 | D485: 市场增长强劲，格局多元化_——2025年中国电梯及扶梯出口分析报告 | E485: http://mp.weixin.qq.com/s?__biz=MjM5MDU1NzI5NQ==&mid=2651538484&idx=1&sn=224ac262f8f3b2495c2ead438010b6cc | F485: 2026-03-17 08:08:33 | G485: 点击蓝字 RECRUIT 关注我们 上图为广告 2025年，中国电梯及扶梯出口行业展现出强劲的增长势头，不仅在出口总量上实现显著突破，市场结构也呈现出多元化和深度拓展的积极态势。 01 全球总览：规模大幅提升，增速最为亮眼 据海关数据，2025年，中国电梯及扶梯的全球出口总量和总产值均实现了显著增长。2025年中国电梯出口量达126833台，总产值约160.11亿元，与2024年出口量102530台，出口量增幅达到24%，与2024年总产值139.96亿元，增幅达到14.4%，电梯出口量和产值均保持了两位数增长，延续高增长态势；扶梯出口量仅13222台，金额30.79亿元，与2024年出口量13462台，总产值29.06亿元，数量有所下降，但产值有小幅增长。 ‌中东、中亚与东南亚需求旺盛，阿联酋以9299台、13.019亿元成为最大市场，俄罗斯、沙特阿拉伯紧随其后，出口量均超6000台。东南亚地区印度尼西亚、越南、马拉西亚、印度等国需求活跃，印度金额达9.495亿元，反映高端产品渗透。 ‌城市化与基建投资驱动增长，中国电梯性价比优势显著。但扶梯市场饱和、区域波动及欧美技术壁垒仍需应对。短期中东、东南亚主导增长；长期需突破欧美高端市场，优化产品创新。 02 市场分析：传统伙伴地位稳固，新兴市场多点开花 中国电梯出口的主要贸易伙伴格局相对稳定，但内部排名和增长动力已发生显著变化。 阿联酋跃升为增长最快的明星市场。2025年，阿联酋市场表现极为突出，电梯出口产值从2024年的约7.8亿元飙升至2025年的13.019亿元，增长幅度惊人，成为2025年最大的亮点。这表明中东地区在基础设施建设上的巨大投入为中国电梯出口带来了前所未有的机遇。 传统市场稳固增长。沙特阿拉伯作为长期的重要伙伴，2025年电梯出口产值再创新高，达到7.55亿元，远超2024年水平。同时，扶梯及步道出口也保持在较高水平，显示其在大型基建项目上的持续需求。俄罗斯市场地位依然稳固，2025年电梯出口产值11.94亿元，整体维持在历史高位，依旧是核心出口市场之一。澳大利亚作为大洋洲最重要的市场，2025年电梯出口产值稳步增长至6.29亿元，体现了其在发达国家市场的竞争力。 东南亚及南亚市场潜力持续释放。印度2025年电梯出口产值达到9.495亿元，较2024年有显著提升，是南亚地区当之无愧的最大市场。印度尼西亚、马来西亚、越南等这些东盟国家在2025年继续保持稳定增长。特别是马来西亚，2025年电梯出口产值7.36亿元，已进入中国全球产值前五行列。菲律宾和泰国的电梯及扶梯进口也呈现稳步上升趋势。 其他区域亮点。中亚哈萨克斯坦和乌兹别克斯坦市场在2025年继续扩大，显示出“一带一路”倡议下中亚地区基础设施互联互通带来的持续红利。美洲哥伦比亚和秘鲁等南美国家在2025年电梯进口量显著增加，成为美洲地区除美国、墨西哥之外的新增长点。墨西哥市场则保持平稳增长。 03 结构分析：电梯主导，扶梯市场稳步发展 从产品类型看，电梯依然是中国出口的绝对主力产品，其出口总值远超扶梯及人行道。2025年，扶梯出口也呈现出稳健的发展态势，主要市场集中在韩国、印度、沙特阿拉伯、土耳其和埃及等国。其中，埃及在2025年的扶梯进口大幅增长，成为非洲地区的最大市场。斯洛伐克在2025年异军突起，成为扶梯出口的一个亮点市场，显示出东欧地区的市场潜力。 小结 1、中国电扶梯出口增长势头强劲。2025年中国国电梯及扶梯出口行业克服了复杂的国际环境，实现了规模和效益的双重提升。 2、市场多元化成效显著。在巩固传统市场的同时，在中东（阿联酋、沙特）、中亚（哈萨克斯坦）、东南亚（马来西亚、越南）等“一带一路”沿线国家取得了突破性进展，有效分散了市场风险。 3、高附加值趋势显现。产值增长超过数量增长，表明出口产品结构正在优化，高附加值产品的国际竞争力增强。 4、潜力市场值得关注。阿联酋已成为新的增长引擎，埃及在扶梯市场的表现、斯洛伐克等东欧国家的崛起，都预示着未来市场的新方向。 展望未来，随着中国电梯企业技术实力和国际竞争力的不断提升，全球基建，特别是“一带一路”的深入推进，电梯及扶梯出口有望继续保持良好发展态势，市场版图将进一步扩大和深化。抓住历史机遇，深耕潜力市场，注重技术创新和品牌建设，在日益激烈的国际竞争中，占据重要地位。 温馨提示 如果你喜欢本文，请分享到朋友圈，想要获得更多信息，请关注我。关于今天的话题，你还有什么想法吗？欢迎留言评论，和我们一起交流哦 saierdt | 赛尔电梯 做电梯，我们更专业致力于成为具有影响力的电梯传播服务机构
A486: 0484 | B486: 合作与展会|广告 | C486: 赛尔电梯 | D486: 跨越山海_为梦同行｜1500人盛会！西奥嘉年会燃动澳门 | E486: http://mp.weixin.qq.com/s?__biz=MjM5MDU1NzI5NQ==&mid=2651538488&idx=1&sn=d7ded3ccd73f9c1ca94afb0da8e30fe2 | F486: 2026-03-19 16:20:51 | G486: 上图为广告 跨越山海聚英豪，为梦同行启新章！3月18日，万众瞩目之下，2026西奥电梯合作伙伴嘉年会盛大启幕，1500位行业大咖齐聚一堂，一场规模空前的行业盛会绽放濠江之畔，刷新电梯行业新纪录！ 星光熠熠，共赴盛宴。西子国际、新西奥电梯集团陈夏鑫董事长，新西奥电梯集团吴华总经理等集团领导，西奥电梯周俊良总裁等公司管理层，携手各战区、各分公司负责人，以及全球各地的忠实伙伴、行业大咖齐聚现场。践行“跨越山海 为梦同行”的初心，大家因信任相聚，因梦想同行，共话发展新机，共赴荣耀征程，携手绘就西奥电梯高质量发展的壮阔蓝图。 奋斗结硕果 极致展新篇 在伙伴共同演绎的我的未来不是梦的燃情舞蹈中，2026嘉年会正式拉开序幕，周俊良总裁登台做主题报告。回望过去五年，在伙伴的鼎力之下，西奥克服经济周期的影响实现跨越式发展，2025年订单量、发运量双双再创新高，持续领跑行业第一阵营，家用梯、更新改造、货梯等细分市场遥遥领先。 “代理商，不是客户，而是命运共同体”，面对全新的市场挑战，我们必须以刀口向内的决心，坚持长期主义、坚守质量底线，追求极致产品品质服务，为伙伴托底，主动跑市场、与伙伴共赢，共同为客户提供最佳解决方案。 周俊良总裁讲到，西奥的每一步跨越、每一份荣光，都离不开合作伙伴的并肩坚守，“全新升级产品和政策方案，将为伙伴更加有力的全方位支持，助力伙伴开拓市场，为伙伴提供最托底的支持”。 同心共荣耀 嘉奖逐梦人 岁月不负奋斗者，荣光致敬追梦人。每一份亮眼的成绩，都离不开伙伴们的一路相随；每一次跨越的突破，都饱含着彼此的赤诚相伴。 颁奖典礼上，十年合作贡献奖、卓越功勋奖等重磅奖项纷呈，千万奖金、豪华旅游，每一份嘉奖都是对伙伴们坚守与付出的最高礼赞，感谢大家多年来的不离不弃、携手奋进，用赤诚与坚守铸就西奥的辉煌。 本次荣耀盛典更首次设立媒体风尚奖，以重金嘉奖那些始终坚守西奥品牌、用心传播西奥品牌声音的合作伙伴。他们是西奥品牌的忠实守护者，更是西奥品牌的金牌代言人，多年来深耕市场、口碑相传，让西奥品牌声量持续放大，与西奥同呼吸、共生长，用实际行动践行品牌初心，助力西奥品牌影响力不断攀升。这份专属殊荣，既是认可，更是期许，未来愿与更多伙伴携手，共筑品牌荣光。 会上，陈夏鑫董事长勉励全体伙伴，中国制造的时代已经来临，风云激荡、方显英雄本色，面对困难与挑战，要坚守初心、勇担使命，继续攀登高峰，携手伟大。 马踏新征程 携手向未来 温情满溢，盛宴启封。精彩纷呈的节目演绎、温馨融洽的举杯同庆，让现场成为欢乐与温情的海洋。大家敞开心扉、共叙情谊，诉说着与西奥的不解情缘，憧憬着未来的美好征程。 跨越山海，初心不改；为梦同行，共筑辉煌。未来，西奥电梯将继续与每一位赤诚相伴的伙伴携手同行，以匠心铸品质，以奋斗创未来，共筑中国制造品牌新高度，共创西奥电梯更加璀璨的明天！ 精 彩 瞬 间 2026 XIOLIFT CONFERENCE 温馨提示 如果你喜欢本文，请分享到朋友圈，想要获得更多信息，请关注我。关于今天的话题，你还有什么想法吗？欢迎留言评论，和我们一起交流哦 saierdt | 赛尔电梯 做电梯，我们更专业致力于成为具有影响力的电梯传播服务机构
A487: 0485 | B487: 技术与产品创新|广告 | C487: 赛尔电梯 | D487: 行业首款主动智能电梯来了！美的家用电梯重新定义家庭垂直出行 | E487: http://mp.weixin.qq.com/s?__biz=MjM5MDU1NzI5NQ==&mid=2651538500&idx=1&sn=ea16cdedaf4fc7c19e1c32940400387a | F487: 2026-03-20 08:01:22 | G487: 点击蓝字 RECRUIT 关注我们 温馨提示 如果你喜欢本文，请分享到朋友圈，想要获得更多信息，请关注我。关于今天的话题，你还有什么想法吗？欢迎留言评论，和我们一起交流哦 saierdt | 赛尔电梯 做电梯，我们更专业致力于成为具有影响力的电梯传播服务机构
A488: 0486 | B488: 广告|合作与展会|技术与产品创新|安装 | C488: 赛尔电梯 | D488: 西奥嘉年会燃动澳门_怡佳_Max_惊艳亮相_借政策东风_焕新老楼出行 | E488: http://mp.weixin.qq.com/s?__biz=MjM5MDU1NzI5NQ==&mid=2651538507&idx=1&sn=62cea994c67a019e2fdf97d31c80bf9b | F488: 2026-03-21 08:49:52 | G488: 上图为广告 跨越山海聚英豪，为梦同行启新章！万众瞩目之下，2026西奥电梯合作伙伴嘉年会华章落幕，再创辉煌，1500位行业大咖齐聚一堂，一场规模空前的行业盛会绽放濠江之畔，刷新电梯行业新纪录！ 作为西奥深耕老旧小区加装电梯领域的标杆力作，怡佳 Max 加装电梯惊艳亮相盛会，凭借大空间、全智能、适老化三大核心优势，成为老旧小区加装电梯的优选方案，用硬核实力诠释西奥对产品的追求，为合作伙伴开拓加装电梯市场注入强劲动力！ 大空间 小尺寸藏大格局，舒适不拥挤 井道尺寸不变 轿厢空间跃升 告别转身的局促 大件搬运也能轻松进出 打破“小井道=挤轿厢”的老印象 让每一次乘梯，都更舒展 全智能 科技护航，便捷又安心 依托鸿燕互联电梯智能管理系统 覆盖乘客、维保、物业等核心场景 支持刷脸、刷卡等多种乘梯方式 智能识别电瓶车，不规范乘梯行为 困人自动报警，快速响应 守护每一次安全乘梯 适老化 为岁月设计，让关怀无声 专为老年群体及特殊人群量身打造 后中壁镜面不锈钢 轿厢后壁扶手、爱心折叠座椅 盲文微光按钮、轿内语音呼梯 让老人出行更安心、更便捷 让温暖与守护，融入乘梯每一刻 2025年12月30日 国家发改委、财政部联合发布 2026年“两新"政策通知 明确将老旧小区加装电梯 纳入超长期特别国债支持范围 标志着加装电梯 升级为国家重点推进的民生工程 乘此东风，西奥将携手全体合作伙伴，以怡佳 Max 为利器，深耕老旧小区加装电梯市场，用硬核产品与贴心服务，为更多老旧小区焕新出行体验，让便捷舒适的乘梯生活惠及千家万户！ 经典项目案例 清华大学 江苏锦明南苑 安徽省合肥市巢湖政协小区 四川省成都市陵川社区 建设部社区 上城区北景西苑7幢1单元 景德镇新枫园小区 柳州颐和家园 温馨提示 如果你喜欢本文，请分享到朋友圈，想要获得更多信息，请关注我。关于今天的话题，你还有什么想法吗？欢迎留言评论，和我们一起交流哦 saierdt | 赛尔电梯 做电梯，我们更专业致力于成为具有影响力的电梯传播服务机构
A489: 0487 | B489: 电梯企业项目 | C489: 赛尔电梯 | D489: 康力电梯荣膺“2026房建供应链综合实力TOP500首选供应商·电梯类”10强！ | E489: http://mp.weixin.qq.com/s?__biz=MjM5MDU1NzI5NQ==&mid=2651538507&idx=2&sn=a4915ae9d694970fcace02bd37cc9d74 | F489: 2026-03-21 08:49:52 | G489: 康力电梯 2026房建供应链综合实力TOP500 首选供应商·电梯类10强 2026年3月18日，以“新深耕时代”为主题的2026中国房地产TOP500测评成果发布会在北京隆重举行，权威发布《2026房建供应链企业综合实力TOP500首选供应商服务商品牌研究成果报告》。 康力电梯凭借稳健的市场表现、建设“好房子”的卓越贡献，连续第14年跻身“房建供应链综合实力TOP500首选供应商·电梯类10强”，2026年稳居行业前3。 康力电梯同时获评“2026房建供应链综合实力TOP500首选供应商·老旧小区改造加装电梯”，彰显公司在城市更新赛道从并跑到领跑。 "十五五"规划纲要，为中国房地产发展指明新方向。 未来五年，民生保障与高质量发展并重，立足人民群众对宜居生活的新期待，推动住房建设从有房住向住好房升级，提升住宅品质、节能水平、智能适配度。 结合城市更新、城中村改造、老旧小区改造，完善配套设施、优化居住环境、提升社区服务，建设好房子、好小区、好社区，打造宜居、韧性、智慧城市，让群众住得安心、舒心、放心。 面对新形势，要有新作为。康力电梯守正创新，视质量为企业的生命线，夯实安全与品质底线，同时积极运用新技术、新工艺、新材料，推动电扶梯技术迭代升级，持续提升用户乘坐体验，是打造“安全、舒适、绿色、智慧‌”好房子进程中，不可或缺的“中国力量”。 值得一提的是，3月3日，康力智慧电梯的探索与应用获CCTV关注：经过康力电梯技术团队的不懈努力，AI技术赋能“会思考”的智慧电梯正在走入人们的生活，让安全守护有温度，让归家脚步更踏实！ 温馨提示 如果你喜欢本文，请分享到朋友圈，想要获得更多信息，请关注我。关于今天的话题，你还有什么想法吗？欢迎留言评论，和我们一起交流哦 saierdt | 赛尔电梯 做电梯，我们更专业致力于成为具有影响力的电梯传播服务机构
A490: 0488 | B490: 技术与产品创新 | C490: 赛尔电梯 | D490: 羿变昊鸿新品发布｜YH-ESSDL-C电梯储能节能装置，硬核解锁电梯绿色节能新方案 | E490: http://mp.weixin.qq.com/s?__biz=MjM5MDU1NzI5NQ==&mid=2651538522&idx=1&sn=96a264d62b3e511d8a8165fc0244653d | F490: 2026-03-22 08:40:38 | G490: 点击蓝字 RECRUIT 关注我们 深耕电梯安全与绿色节能领域，羿变昊鸿历经2年研发攻关与实梯验证，正式发布YH-ESSDL-C 系列电梯储能节能装置！这款专为非四象限 VVVF 电梯打造的节能利器，采用基于自产SiC功率模块的双向DC/DC变换技术，实现电梯发电电能的智能回收与回送，以硬核技术助力绿色建筑升级，共筑低碳经济发展新格局。 YH-ESSDL-C 电梯储能节能装置只需连接2根导线至电梯变频器直流母线，即可全天候自动运行。其核心搭载三相交错并联 BUCK-BOOST 双向 DC/DC 变换器，采用超级电容为储能介质，安全可靠。当电梯轻载上行或重载下行处于再生发电状态时，节能装置将原本由制动电阻消耗的电能自动充电储存在超级电容中；而当电梯轻载下行或重载上行处于电动状态时，节能装置将储存与超级电容中的电能回送至电梯变频器直流母线，替代部分电网供电，从而实现节省耗电的目标。 完整系列 针对不同供电电压、载重量、梯速的电梯，可通过我们提供的节电率计算软件选型，以获得最佳节电性价比。 400V级产品 200V级产品 物联支持，节能量化 ESSDL配备4位LED显示与操作按钮，实时查看超容/母线的电流、电压，以及累计节电量等关键参数。ESSDL配置了RS485、CAN、CAN-open通讯接口，RS485搭载Modbus协议，连接网关即可将数据发送至云端。 多重防护，运行安全更可靠 ESSDL内置高压侧过压 / 欠压、低压侧过压 / 欠压、过流、过热等八大保护功能，触发保护条件时自动切换状态并报警，有效保护设备与电梯控制系统，杜绝安全隐患。 不存在电力监管风险 对比回馈式节能装置，YH-ESSDL-C对电网无任何污染、不存在大量回馈式装置同时工作时可能造成电网崩溃的风险、也不存在并网运行带来的电网监管风险，因此更具核心竞争优势。 高效顶流技术团队 羿变昊鸿技术团队由武汉羿变电气有限公司与宁波昊鸿电子有限公司共同打造，是一支产学研深度融合的创新力量。依托华中科技大学电气与电子工程学院的雄厚科研背景，由华中科技大学资深教授康勇担任首席科学家，核心成员包括章正、陈材、黄志召、段三丁等资深科研骨干共50余人，硕士及以上学历占比超20%。其中以90后高学历青年为主力、平均年龄不足30岁，兼具前沿创新活力与工程技术应用沉淀。 绿色是建筑发展的主旋律，节能是电梯运营的新趋势。羿变昊鸿将持续凭借技术创新硬实力，为电梯安全与绿色节省提供不断优化的解决方案，与合作伙伴共同助力绿色建筑、共创低碳经济！ 羿变昊鸿永远激励自己：我们为您做的，远比契约更多！ 温馨提示 如果你喜欢本文，请分享到朋友圈，想要获得更多信息，请关注我。关于今天的话题，你还有什么想法吗？欢迎留言评论，和我们一起交流哦 saierdt | 赛尔电梯 做电梯，我们更专业致力于成为具有影响力的电梯传播服务机构
A491: 0489 | B491: 电梯企业项目|维保 | C491: 迅达电梯 | D491: 28天焕新老旧电梯！迅达助力武汉美景天城老旧小区更新改造 | E491: http://mp.weixin.qq.com/s?__biz=MzcwNjA1OTI1Mw==&mid=2247499897&idx=1&sn=58d8ca6662006e55567d8860230fa440 | F491: 2026-03-20 15:27:12 | G491: 迅达电梯全生命周期解决方案\x0d 助力更多老小区实现 “优居” 梦想！
A492: 0490 | B492: 地方政策与补助 | C492: 迪斯卡电梯 | D492: 山西“两新”政策落地！将老旧小区加装电梯、换购新能源车等民生安全领域纳入扩围重点 | E492: http://mp.weixin.qq.com/s?__biz=Mzg4MDEwNTkwOQ==&mid=2247490266&idx=3&sn=6b490882d87cb96a94a6da10d38c19fc | F492: 2026-03-20 14:56:06 | G492: 小区电梯加装 【点击此处了解】 诚招全国区域合作 【点击此处了解】 *迪斯卡加装电梯案例 为了持续推进我省大规模设备更新和消费品以旧换新，有力释放内需潜力、扩大有效投资，3月18日，山西晚报·山河＋记者从省发改委和省财政厅获悉，我省发布了《山西省2026年实施大规模设备更新和消费品以旧换新政策行动方案》，将老旧小区加装电梯、换购新能源车等民生安全领域纳入扩围重点，通过“设备更新、消费焕新”双轮驱动，全力释放内需潜力，筑牢安全底线，托举百姓幸福生活。 01 力推老旧小区电梯加装扩围 我省将继续全面推进大规模设备更新，包括持续加大既有支持领域设备更新力度，紧跟国家政策导向，围绕国家2026年扩围支持的老旧小区加装电梯、养老机构、消防救援设施、检验检测及线下消费商业设施设备更新等领域，加快行业调研和需求摸底，对接国家政策精准谋划一批成熟项目，更好满足民生和安全需要。重点推进既有住宅加装电梯，完善适老化改造，方便居民出行。推动养老机构护理床位、康复器械、安全监护、智慧管理等设备升级改造。支持消防救援部门更新特种车辆、个人防护、智能救援等装备。 深入推进营运货车、城市公交车和农机设备报废更新。继续鼓励报废国四及以下排放标准营运货车更新为低排放货车，优先支持更新为电动货车，推动新能源重卡规模化应用，提高重点行业大宗货物清洁运输比例。推动城市公交车电动化替代，鼓励公交企业发展绿色公交、智慧公交，支持超过质保期的动力电池安全有序更换。聚焦机播增产和机收减损，结合农业生产需要和农业机械化发展水平，支持报废更新先进适用、节能环保、安全可靠的农业机械。 据悉，我省支持报废国四及以下排放标准营运货车，加快更新为新能源货车（包括纯电动、插电式混合动力、氢能货车）和符合国六排放标准的低排放货车（包括柴油、甲醇、燃气货车），优先支持更新为电动货车。报废并更新购置符合条件的货车，平均每辆车补贴8万元；无报废只更新购置符合条件的货车，平均每辆车补贴3.5万元；只提前报废老旧营运类柴油货车，平均每辆车补贴3万元。 02 换购新能源车最高补贴1.5万 深入实施提振消费专项行动，促进大宗消费更新升级。支持汽车报废更新、汽车置换更新、6类家电以旧换新（冰箱、洗衣机、电视、空调、电脑、热水器）、4类数码和智能产品购新（手机、平板、智能手表/手环、智能眼镜），补贴标准按照全国统一要求执行。在全国消费品以旧换新政策框架内，结合我省实际，适当增加补贴品类，支持能效、水效、环保水平高的产品，重点支持国务院“人工智能+”行动明确的新一代智能终端，补贴标准、组织实施方式另行制定。贯通消费品产业链，推进消费品工业增品种、提品质、创品牌，打造消费品特色园区。 山西晚报·山河＋记者了解到，对个人消费者通过售卖方式转让登记在本人名下的乘用车，并购买纳入工业和信息化部《减免车辆购置税的新能源汽车车型目录》的新能源乘用车或2.0升及以下排量的燃油乘用车，给予一次性补贴。对换购符合上述条件新能源乘用车的，按新车销售价格的8%给予补贴，补贴金额最高1.5万元；对换购符合上述条件燃油乘用车的，按新车销售价格的6%给予补贴，补贴金额最高1.3万元。参与申请补贴的乘用车旧车所有人和新购置乘用车所有人应为同一个人消费者。所转让的乘用车旧车，应当于2025年1月8日前登记在申请人名下。 对个人消费者购买的以下6类家电新产品给予补贴，产品须符合国家一级能效或水效标准：冰箱（含冰柜、冰吧）、洗衣机（含洗烘一体机）、电视、空调（含家用中央空调、空气能采暖机）、热水器、电脑（含台式电脑、笔记本电脑，不含自行组装的兼容机）。每位消费者在政策执行期内，每类产品限补贴1件（线上线下渠道合并计算）。补贴标准为扣除所有环节优惠后最终销售价格的15%，家电产品每件补贴金额不超过1500元。2025年已享受上述产品补贴的个人消费者，2026年购买同类产品可继续享受补贴。 对个人消费者购买单件销售价格（含税）不超过6000元的手机、平板（含具有学习功能的智能教育平板）、智能手表（手环）、智能眼镜（含AR/VR头戴式显示设备）等4类数码和智能产品给予补贴。每位消费者在政策执行期内，每类产品限补贴1件（线上线下渠道合并计算）。补贴标准为扣除所有环节优惠后最终销售价格的15%，数码和智能产品每件补贴金额不超过500元。2025年已享受上述产品补贴的个人消费者，2026年购买同类产品可继续享受补贴。 03 完善回收循环利用体系 我省将提升废弃物循环利用能力，支持汽车、电子产品、家电家具等回收体系建设，推广“互联网+回收”、社区智能回收柜、“以车代库”等模式。畅通废旧设备和消费品交售渠道，推进再生资源交投点、中转站和分拣中心建设。充分发挥供销合作社基层经营服务网点优势，完善基层回收网络覆盖。推动有条件的生产、销售企业开展废旧产品逆向物流回收。支持废旧动力电池、退役风电光伏设备、数据中心及通信基站等新型基础设施领域废弃物循环利用。加强资源循环利用重大技术装备科技攻关。加大再生材料推广应用，推进政府采购再生资源产品，引导生产企业提高再生材料应用比例。依法依规严厉查处非法回收拆解活动。落实资源回收企业向自然人报废产品出售者“反向开票”，规范资源回收企业税收监管。 与此同时，我省还将继续规范二手商品流通和再制造，鼓励“互联网＋二手”模式发展，支持回收企业借助相关信息平台、移动应用程序等开展“线上预约、线下回收”，鼓励建设集中规范的线下二手商品交易市场，促进二手商品流通市场发展。加强计算机类、通讯类和消费类电子产品二手交易的信息安全监管。加快推进再制造产业培育，探索推进废旧机电设备、汽车零部件等再制造，加强再制造共性关键技术的创新研发和推广应用。 来 源：山西晚报 免责声明：文章内容如涉及作品内容、版权和其它问题，请在30日内与本公众号联系，我们将在第一时间删除内容 小区电梯加装 【点击此处了解】 诚招全国区域合作 【点击此处了解】
A493: 0491 | B493: 地方政策与补助|安装 | C493: 迪斯卡电梯 | D493: 重磅！事关吉林省延边州老旧小区加装电梯……（附：申请方式） | E493: http://mp.weixin.qq.com/s?__biz=Mzg4MDEwNTkwOQ==&mid=2247490266&idx=4&sn=8d03258558dcfd0b495ae6a0d8ec0368 | F493: 2026-03-20 14:56:06 | G493: 小区电梯加装 【点击此处了解】 诚招全国区域合作 【点击此处了解】 *迪斯卡加装电梯案例 既有住宅加装电梯，是吉林省委、省政府确定的重大民生实事，是提升城市品质、积极应对人口老龄化、回应群众期盼的重要举措。延边州委、州政府对此高度重视，将其纳入“延边美好生活”十大工程高位推进。自上级部署以来，我州迅速响应，率先制定印发《延边州既有住宅加装电梯工作的实施意见》及系列配套文件，这标志着全州加装电梯工作正式从“谋划准备”阶段转入“全面实施”阶段。 记者从有关部门了解到，为确保电梯“装得上、用得好、管得久”，既有住宅加装电梯工程坚持“业主主体、政府引导，建管并重、保障安全，能加尽加、愿加快加”的原则，实施项目化、工程化管理，建立健全从加装到运维的全生命周期管理机制。 加装一部电梯需要多少钱？ 为了让群众装得起电梯，我州通过带量采购、集中议价，确定了“基础款”（半层入户）电梯35万元左右的“拦标价”。但这个价格不包括管线排迁费用，管线排迁将结合老旧小区改造、老化管道更新“一事一议”解决。如果居民要求更高标准，比如平层入户、进口主机等，超出部分由居民协商分摊。 加装电梯的钱从哪里来？ 建立“业主出资、政府补助、多方支持”的资金筹措机制。一是政府补助，省级、市（州）两级财政给予适当补助，这笔钱在取得施工许可后，会拨付到业主、EPC总承包商、地方政府三方共管账户，确保资金安全；二是业主出资，按照“谁受益、谁出资，受益大、出资多”的原则，不同楼层业主协商分摊，具体可灵活调整，同时业主及其配偶、父母、子女可提取住房公积金，经同意也可使用住宅专项维修资金；三是多方支持，金融机构会推出相关贷款产品，原产权单位可给予支持，管线单位可减免或按成本价收取迁移费，同时还免征相关行政事业性收费和政府性基金。 什么房子可以加装电梯？ 既有住宅加装电梯的单元应为国有建设用地上依法建设、权属清晰、未列入房屋征收或改造计划的四层及以上无电梯的多层既有住宅，不属于单一产权、个人自建房；以及单位自管公房、政府持有的保障房；且经具备相应资质的专业机构鉴定，符合房屋结构、消防条件等安全要求。 加装电梯有哪些主要流程？ 需要加装电梯的住宅，首先，可按小区、楼栋或单元为单位组织；多业主住宅单元有一户申请，即可启动本单元加梯意愿征询；单位自管公房、政府持有的保障房，产权人同意即可申请加装电梯。然后是表决签约环节，达到“双2/3参与，双3/4同意”的法定表决比例后，引导业主确定实施方案，内容包括但不限于加梯设计方案、加梯和运维费用分担方案、后续运维管理等，并组织公示。同意加装电梯的业主作为工程建设单位，可授权委托业主代表、业主委员会或社区居委会等作为代理业主，负责办理加装电梯相关事项，授权委托内容包括但不限于项目申请、合同签订、工程实施、工程验收等。进入审批与建设程序后，业主应委托具备相应资质的专业机构，对住宅单元房屋结构、消防等条件是否具备加装电梯要求开展检测鉴定。然后经过联合审查、规范施工、竣工验收等环节，即可完成电梯加装工程，并进入运行维护阶段。届时，有物业小区，委托物业企业为电梯使用管理单位；无物业的，按照“统一标准、连片托管”模式，委托专业运营机构作为电梯使用管理单位，负责加装电梯的登记、日常使用和运行管理以及电梯维护保养。 按照工作安排： 3月底前要完成意愿征集、方案确定等前期工作； 4月底前，延吉市试点项目开工建设，形成可复制经验； 6月底前，30%的任务计划进入土建施工阶段； 8月底前，年度任务计划全部开工； 11月底前，全面完成竣工验收。 广大市民可在“吉事办”小程序中搜索“既有住宅加装电梯”，了解加梯流程、政策咨询电话或者进行加梯申请。 01 02 03 费用: 省委、省政府将既有住宅加装电梯列入2026年重点民生实事，拿出省级财政资金重点保障；州委、州政府在安排专项配套资金基础上，积极构建“政府补助、业主共担、金融支持”的多元筹措体系。各级财政将结合实际，确定本级配套补助政策。同时，将紧抓“两新”超长期特别国债支持加装电梯的政策窗口，全力争取资金支持，资金来源实现了多元化。除了省、州（市）、县级财政补贴外，还可以使用物业维修基金、住房公积金、“加梯贷”等普惠金融产品。 值得一提的是，公积金的使用范围也已放宽，不仅限于本人，还可以提取子女等家庭成员的公积金，以切实降低居民加梯成本。 来 源：延边新闻、延边日报 免责声明：文章内容如涉及作品内容、版权和其它问题，请在30日内与本公众号联系，我们将在第一时间删除内容 小区电梯加装 【点击此处了解】 诚招全国区域合作 【点击此处了解】
... A495: 0493 | B495: 地方政策与补助|合作与展会 | C495: 迪斯卡电梯 | D495: 已施行《拉萨市既有住宅加装电梯管理办法（试行）》最高补贴25万_台 | E495: http://mp.weixin.qq.com/s?__biz=Mzg4MDEwNTkwOQ==&mid=2247490266&idx=2&sn=7dbcf36d133d7a07cc43aaae1ca765f5 | F495: 2026-03-20 14:56:06 | G495: 小区电梯加装 【点击此处了解】 诚招全国区域合作 【点击此处了解】 *迪斯卡加装电梯案例 日前 拉萨市住房和城乡建设局官网发布 《拉萨市既有住宅 加装电梯管理办法（试行）》 该办法自2026年3月1日施行 有效期为2年 详情如下 ↓↓↓ 拉萨市既有住宅加装电梯管理办法（试行） 第一章总则 第一条 为适应经济社会发展和人口老龄化需求，完善城市既有住宅使用功能，提升居住品质，保障和改善民生，根据《中华人民共和国民法典》《中华人民共和国无障碍环境建设法》《中华人民共和国特种设备安全法》《中华人民共和国建筑法》《中共中央办公厅 国务院办公厅关于持续推进城市更新行动的意见》等法律法规和政策规定，结合拉萨市实际，制定本办法。 第二条本市行政区域内既有住宅加装电梯工作遵循“政府引导、业主主体、社区搭台、多方协同、安全为本、保障民生”的原则，实行民主协商、联合审查、依法实施、长效管理的工作机制，突出“业主自愿、业主自治”核心地位。 第三条 本办法适用于拉萨市行政区域内既有住宅加装电梯的建设和管理，同时既有住宅须满足以下条件：（一）既有住宅建筑为非单一产权；（二）已竣工验收并投入使用的合法建筑，且已取得房地产权属证明文件；（三）建筑总层数为四层及以上，地下室不计入总层数；（四）未列入房屋征收改造规划范围或计划。住宅小区基础设施和功能明显不足的保障性住房、单位自管房、公有住房需要加装电梯的，可参照本办法实施程序执行。 第四条 既有住宅加装电梯应当经过拟加装电梯所在单元业主的协商。既有住宅加装电梯的意向和建筑设计方案应当听取拟加装电梯所在物业管理区域范围内业主的意见，并应当经加装电梯所在单元房屋专有部分面积占比三分之二以上的业主且人数占比三分之二以上的业主参与表决，经参与表决专有部分面积四分之三以上的业主且参与表决人数四分之三以上的业主同意。拟占用业主专有部分的，还应当征得该专有部分的业主同意。 第五条出资加装电梯的业主作为法定实施主体，应依法承担电梯建设安装、竣工验收、运维管理及安全运行等全流程法律责任。项目申报应由实施主体确定的电梯使用管理者进行申报。电梯使用管理者是指由实施主体书面委托业主委员会、物业服务企业、电梯生产企业或具有相应资质的单位代为实施。书面委托须签订委托协议，明确双方权利义务。 第六条委托人应与受托人签订委托协议，明确双方权利义务。加装电梯项目协议书应明确项目电梯管理责任人及实施主体的职责、项目建设资金估算及分摊方案、电梯运行使用和维护保养资金分摊方案、权益受损业主补偿方案等内容。 第二章职责分工 第七条 县（区）人民政府负责组织领导、协调推进本辖区内既有住宅加装电梯工作，健全工作机制，落实、发放补助资金。自然资源、住房城乡建设、市场监管等行政管理部门按照各自职能做好既有住宅加装电梯的审批和管理工作。 第八条 住房和城乡建设部门统筹协调既有住宅加装电梯工作，负责制定配套政策、监督指导实施进程、协调土建施工技术标准等工作。市场监督管理部门负责核查电梯安装单位施工告知，按照“双随机、一公开”方式对电梯使用单位实施监督检查，履行特种设备安全监督管理职责。财政部门负责市级补助资金的筹集、管理和监督，保障补助资金预算安排。自然资源部门负责既有住宅加装电梯的用地规划管理工作，开展规划符合性审查及规划许可豁免相关工作。城市管理和综合执法部门、消防救援支队、国网电力公司、自来水、燃气、通信网络等相关单位按职责参与现场踏勘、联合审查与验收。各职能部门应建立联动机制，推行“一窗式”受理、审批、办结，优化审批流程。 第九条街道办事处（乡镇人民政府）负责既有住宅加装电梯的政策宣传、业务指导、矛盾协调，组织公示、协助成立业主自治组织（如加装电梯自治改造委员会）、出具公示结果确认函等。社区居民委员会负责公示意见收集、平台搭建、异议调解和报告街道办事处等工作。业主委员会、物业服务企业应积极配合实施主体开展意见征询、方案公示、现场踏勘、信息沟通等工作。 第三章资金筹集与管理 第十条 加装电梯所需建设及可能产生的管线迁移等费用，由本单元（幢）相关业主根据所在楼层、面积等因素共同协商，按合理比例分摊。 第十一条 资金来源主要包括： （一）业主按分摊协议自筹资金； （二）业主可依法申请使用住宅专项维修资金； （三）业主及其配偶、父母、子女可依法申请提取住房公积金账户内的存储余额，提取总额不超过个人出资金额； （四）社会资本投资、金融机构信贷支持、电梯商业广告收入等其他合法资金来源。既有住宅原建设单位可以出资加装电梯。 第十二条 加装电梯政府按照加装总费用的50%，最高不超过25万元给予补贴，超出部分由业主自行承担。政府补贴资金由市、县（区）两级财政按1:1比例分担。加装电梯项目竣工验收备案并正式投入使用、取得《特种设备使用登记证》后向属地住建部门申请加装电梯补助资金。 第十三条 实施主体应设立加装电梯资金共管账户或托管账户，统一管理建设资金。所有资金筹措方案、分摊明细、使用情况及财政补贴发放情况，接受全体业主及社区居委会监督，在小区显著位置进行公示，公示期不得低于15日。全部或部分使用国有资金投资或国家融资的加装电梯项目，若符合依法必须招标的工程建设项目范围和规模标准，应严格按照政府采购、招标投标相关法律法规和规章的规定执行。 第四章实施管理 第十四条 既有住宅加装电梯应当按照申请、联合踏勘审查、编制施工图、组织公示等程序进行。 （一）申请。符合条件的实施主体，应确定电梯使用管理者向项目所在地住建部门提交加装电梯的书面申请。同时须提交房屋权属证明、经全体业主签署的加装电梯协议书、街道和社区意见书、确定电梯使用管理者协议（含管理者相关证明文件）、加装电梯工程费用的预算及其筹集方案、电梯维护保养方式及其保养维修费用分担方案、与不同意加装电梯的业主进行协商，以及对利益受损业主进行补偿的资金筹集方案、初步意向方案（含平面图、立面图、效果图及位置、尺寸说明）等材料。 （二）联合踏勘审查。属地住建部门在收到申请后15个工作日内，应组织自然资源、消防部门、市场监管、城管部门、电力、管线单位、街道办事处（乡镇人民政府）等单位（部门）进行联合现场踏勘并召开联席会议，重点审查规划、建筑结构、消防安全、电力容量、管线迁移可行性、电梯设备选型（参数、安全性能）及安装方案等，并形成加装电梯的书面审查评估意见。 （三）编制施工图。项目申请单位应委托具备相应资质的设计单位编制详细的施工图设计文件（包括总图、结构、电气、消防等），无原房屋建筑地质勘察报告的应委托有资质的勘察单位进行现场确认。设计方案应符合建筑设计、结构安全、电梯救援通道、消防安全和特种设备等相关规范、标准。鼓励采用占地少、工期短、噪音低、工业化程度高的整体装配式电梯方案，同一小区内加装电梯应保持外观、风格协调。施工图经有资质的审查机构审查合格后报送住建部门备案。 （四）组织公示。街道办事处（乡镇人民政府）将审查通过的设计方案在本单元及小区显著位置公示不少于5个工作日，公示期满无实名书面异议的，由街道办事处（乡镇人民政府）出具公示确认书后即可办理工程规划许可证、施工许可证等施工许可后组织施工，施工过程中由属地住建部门同步开展质量安全监督。公示期间若有实名书面异议，由街道办事处（乡镇人民政府）、社区居民委员会组织协调，建立“业主协商、社区调解、街道调解”的三级异议调解机制。经协商未能达成一致意见的，实施主体应继续与异议人进行不少于两次的沟通协商，并形成记录，协商情况应在公示报告中说明。 第十五条实施主体应选定具备相应资质的施工承包单位（含土建及电梯安装资质）和符合国家标准的电梯设备，委托具备资质的监理单位负责工程监理，签订施工合同和监理合同。 第十六条 施工单位应在施工前，将资质文件、施工方案（含安全措施、施工时段、降噪防尘等文明施工要求）向项目所在地住建部门、市场监管部门履行备案程序，并向特种设备检验机构申报安装监督检验。施工过程中应采取整体吊装或组装方式，严禁现场除锈和喷漆作业。电梯的安装，应由制造单位或者其委托并依法取得相应许可的单位实施，制造单位委托其他单位进行电梯安装的，应进行安全指导和监控，按要求校验调试，对电梯安全性能负责。 第十七条 工程完工后，实施主体应组织设计、施工、监理等单位进行项目专项验收，并形成工程档案。电梯安装完成投入使用前，实施主体应依法组织竣工验收，验收合格后及时向住建部门备案。同时，实施主体必须持监督检验机构出具的验收检验报告和安全检验合格标志，到项目所在地市场监管部门提交电梯技术档案并办理使用登记。电梯安装竣工并经监督检验合格后30日内，施工单位应向电梯使用单位移交质量合格文件和有关技术资料，并提供不少于一年的免费日常维护保养。 第十八条 实施主体或其委托的电梯使用管理单位（如物业服务企业、专业维保公司）依法承担电梯安全管理的主体责任，履行日常安全管理职责。 第五章产权与相关事项 第十九条 加装的电梯及井道等附属设施属于本单元（幢）出资业主共有，共有范围按照协议约定。不再另行办理不动产登记，不变更原分户业主产权面积、用地面积。业主转让房屋时，应告知受让人电梯共有情况、费用分摊义务及相关权利义务，受让人承继原业主的权利与义务。 第二十条 既有住宅加装电梯部分不纳入所在小区容积率核算范围，不计入房屋建筑面积。 第二十一条 加装电梯应尽可能减少对小区环境、相邻建筑、城市景观及消防通道的影响，不得占用城市道路等公共空间，不得影响楼梯间安全疏散通道。原则上不得沿城市道路侧加装电梯，避免出现与周边风貌不协调以及影响城市景观的情况。严禁通过加建改建等方式扩大住宅套内使用面积，不得将候梯厅变为独用空间。加装电梯应尽量减少对相邻业主通风、采光、日照、通行等不利影响；造成不利影响的，应依法给予补偿。 第六章争议解决 第二十二条 业主间因加装电梯产生的争议，应首先通过协商解决。协商不成的，可请求街道办事处（乡镇人民政府）、社区居民委员会或相关人民调解组织调解。仍无法达成一致的可依法通过民事诉讼等途径解决。对恶意阻挠、破坏施工或扰乱公共秩序的，由公安机关依法处置。 第七章附则 第二十三条 本办法具体应用中的问题由拉萨市住房和城乡建设局会同相关部门负责解释。 第二十四条 本办法自2026年3月1日施行，有效期为2年。在施行期间，如遇国家法律法规或上级政策调整，应按最新规定执行。 来 源：拉萨市住房和城乡建设局 免责声明：文章内容如涉及作品内容、版权和其它问题，请在30日内与本公众号联系，我们将在第一时间删除内容 小区电梯加装 【点击此处了解】 诚招全国区域合作 【点击此处了解】
A496: 0494 | B496: 其他 | C496: 通力电梯 | D496: 通力30年｜回头有故事，向前有惊喜 | E496: http://mp.weixin.qq.com/s?__biz=MjM5ODQ4MjU4OQ==&mid=2653309821&idx=1&sn=8b3ff906ea4ae028856cfbc51b04f5fc | F496: 2026-03-20 10:19:49
A497: 0495 | B497: 维保|政府行政令 | C497: 闽梯圈 | D497: 龙岩市市场监督管理局：关于2025年度电梯维保质量安全信用等级评价结果通报 | E497: http://mp.weixin.qq.com/s?__biz=Mzg2Mjc1NDA3OQ==&mid=2247492996&idx=1&sn=f786fda9b4324a90ae48a0e61295bcc5 | F497: 2026-03-16 10:06:25 | G497: 各 县 （ 市 、 区 ） 市 场 监 管 局 、 经 开 区 分 局 ， 福 建 省 特 检 院 龙 岩 分 院 ， 龙 岩 市 电 梯 行 业 协 会 ， 有 关 电 梯 使 用 、 维 保 、 检 测 单 位 ： 根 据 《 福 建 省 市 场 监 督 管 理 局 关 于 印 发 福 建 省 电 梯 维 保质 量 安 全 信 用 管 理 办 法 的 通 知 》 （ 闽 市 监 规 〔 2 0 2 2 〕 7 号 ）（ 以 下 简 称 《 办 法 》 ） 和 《 龙 岩 市 市 场 监 督 管 理 局 关 于 开 展2 0 2 5 年 度 电 梯 维 保 质 量 安 全 信 用 等 级 评 价 的 通 知 》 （ 岩 市 监〔 2 0 2 5 〕 1 6 9 号 ） 要 求 ， 我 局 组 织 对 全 市 电 梯 维 保 单 位 在 2 0 2 5年 度 有 关 许 可 管 理 、 资 源 条 件 、 质 量 保 证 体 系 、 维 保 质 量 、检 验 检 测 、 监 督 检 查 、 应 急 救 援 、 事 故 情 况 、 智 慧 管 理 、 机制 创 新 、 维 保 质 效 、 保 险 服 务 、 公 益 服 务 等 1 3 类 4 0 个 项 目进 行 质 量 安 全 信 用 等 级 评 价 （ 以 下 简 称 “ 等 级 评 价 ” ） ， 现将 相 关 评 价 情 况 通 报 如 下 : 一 、 评 价 结 果 全 市 参 加 评 价 电 梯 维 保 单 位 5 2 家 ， 其 中 本 地 注 册 法 人 机构 3 4 家 ， 外 地 分 支 机 构 1 8 家 。 福 建 金 纳 三 菱 电 梯 有 限 公 司等 5 家 单 位 因 未 开 展 维 保 业 务 ， 不 参 加 本 次 等 级 评 价 。 经 综合 评 价 ， 获 评 A 级 1 7 家 、 B 级 2 家 、 C 级 3 2 家 、 D 级 1 家 。与 去 年 相 比 ， 总 参 评 单 位 减 少 8 家 ， 评 为 A 级 减 少 3 家 ， B级 增 加 1 家 ， C 级 减 少 2 家 ， D 级 减 少 4 家 。 ( 详 见 表 1 、 附件 1 、 2 ） 表 1 ： 2 0 2 5 年 龙 岩 市 电 梯 维 保 质 量 安 全 信 用 等 级 评 价 情 况 注册地 总数 A级 B级 C级 D级 本地机构 34 11 2 21 0 外地驻岩机构 18 6 0 11 1 合计 52 17 2 32 1 二 、 总 体 情 况 大 部 分 电 梯 维 保 单 位 能 较 好 地 贯 彻 执 行 《 中 华 人 民 共 和国 特 种 设 备 安 全 法 》 《 福 建 省 电 梯 安 全 管 理 条 例 》 等 法 律 法规 和 安 全 技 术 规 范 ， 在 许 可 管 理 、 资 源 条 件 和 质 量 保 证 体 系等方 面 能 够 较 好 地 满 足 要 求 ， 在 推 进 电 梯 公 益 宣 传 、 保 险 服务 、 智 慧 管 理 等 方 面 有 进 一 步 的 提 升 ， 在 推 广 全 包 制 保 养 ，集 使 用 、 维 保 安 全 主 体 责 任 为 一 体 的 创 新 管 理 模 式 方 面 获 得突 破 。 全 市 电 梯 定 期 检 验 一 次 检 验 合 格 率 为 9 5 . 2 3 % ， 维 保 与运 行 质 量 监 督 抽 查 合 格 率 为 8 0 . 6 5 % ， 较 往 年 基 本 持 平 。 全 市共 有 6 1 4 6 余 台 电 梯 实 现 运 行 情 况 远 程 监 测 、 数 据 采 集 和 故 障预 警 诊 断 ， 电 梯 维 保 质 量 智 慧 管 理 水 平 进 一 步 得 到 提 升 。 三 、 存 在 问 题 （ 一 ） 资 源 条 件 与 质 量 保 证 体 系 方 面 。部 分 单 位 质 保 体系 人 员 数 量 不 符 合 要 求 、 存 在 人 员 离 职 未 及 时 补 充 任 命 等 问题 。 部 分 外 地 驻 点 分 支 机 构 未 按 3 5 台 / 人 （ 按 需 维 保 的 5 0台 / 人 ） 配 备 持 证 维 保 人 员 ， 未 配 备 与 维 保 业 务 相 适 应 仪 器 、备 品 备 件 或 仪 器 未 定 期 校 验 。 未 及 时 开 展 管 理 评 审 ， 并 按 照相 关 法 律 法 规 要 求 对 质 保 体 系 进 行 修 订 。 组 织 对 质 保 体 系 人员 培 训 教 育 考 核 缺 乏 针 对 性 、 实 效 不 佳 ， 质 保 工 程 师 、 质 量安 全 总 监 和 质 量 安 全 员 对 质 保 体 系 和 岗 位 责 任 落 实 不 到 位 。 （ 二 ） 维 保 质 效 方 面 。一 是 维 保 方 案 制 定 不 合 理 。部 分单 位 未 能 严 格 按 照 厂 家 安 装 使 用 维 护 说 明 书 要 求 并 结 合 所 保养 电 梯 实 际 情 况 ， 制 定 合 理 的 维 保 计 划 和 方 案 ， 尤 其 是 按 需维 保 的 电 梯 ， 存 在 少 部 分 电 梯 远 程 监 测 装 置 失 效 、 未 依 据 实时 线 上 检 查 和 监 测 维 护 情 况 ， 采 取 针 对 性 的 线 下 现 场 维 护 保养 ， 维 护 保 养 的 科 学 性 和 有 效 性 有 待 提 高 。二 是 对 维 保 质 量不够 重 视 ， 内 部 抽 查 管 理 制 度 落 实 效 果 欠 佳 。 部 分 维 保 单 位缺 乏 有 效 的 内 部 管 理 手 段 ， 未 按 安 全 操 作 规 范 （ 落 实 劳 动 保护 措 施 ） 进 行 维 保 作 业 等 违 法 行 为 时 有 发 生 ； 维 保 质 量 内 部抽 查 未 能 覆 盖 全 体 维 保 人 员 ， 维 保 缺 项 以 及 维 保 走 过 场 的 情形 还 存 在 ， 如 个 别 维 保 项 目 缺 少 检 查 轿 厢 内 紧 急 照 明 、 五 方通 话 等 报 警 装 置 的 功 能 ， 未 对 限 速 器 - 安 全 钳 联 动 试 验 有 效 性进 行 验 证 ， 对 重 侧 导 靴 油 杯 缺 油 、 漏 油 ； 公 共 聚 集 场 所 和 住宅 小 区 部 分 电 梯 轿 厢 未 设 置 符 合 要 求 的 视 频 监 控 设 施 ； 部 分自 动 扶 梯 与 自 动 人 行 道 存 在 电 梯 入 口 或 出 口 未 设 置 能 够 监 控电 梯 运 行 全 行 程 的 视 频 监 控 设 施 ， 驱 动 与 转 向 站 内 有 杂 物 、积 水 ， 出 入 口 运 行 方 向 显 示 功 能 失 效 ， 梳 齿 板 梳 齿 缺 损 、 刮擦 等 问 题 。三 是 未 及 时 将 电 梯 使 用 单 位 安 全 主 体 责 任 履 行 不到 位 问 题 上 报 市 场 监 管 部 门 。部 分 使 用 单 位 安 全 保 障 资 金 投入 不 足 ， 如 电 梯 轿 厢 内 视 频 监 控 设 施 、 远 程 监 测 装 置 、 机 房通 风 降 温 设 施 失 效 等 电 梯 相 关 失 效 配 件 未 及 时 修 复 ； 部 分 使用 单 位 未 及 时 对 发 现 的 电 梯 异 常 情 况 进 行 全 面 检 查 或 及 时 处置 。 （ 三 ） 监 督 检 查 与 检 验 检 测 方 面 。近 年 来 ， 全 市 电 梯 定期 检 验 一 次 检 验 合 格 率 、 维 保 与 运 行 质 量 监 督 抽 查 合 格 率 虽基 本 保 持 平 稳 ， 但 仍 存 在 部 分 单 位 合 格 率 偏 低 拖 后 腿 ， 甚 至连 续 几 年 合 格 率 低 于 7 5 % 的 情 况 ， 其 中 包 含 了 较 多 维 保 原 因导 致 的 电 梯 定 期 检 验 不 合 格 的 情 形 。 2 0 2 5 年 度 ， 在 市 局 组 织的 以 维 保 质 量 安 全 信 用 等 级 分 类 实 施 监 管 中 ， 还 存 在 多 家 单位未 按 照 技 术 规 范 要 求 开 展 维 保 ， 依 靠 降 低 维 保 质 量 低 价 竞争 被 立 案 查 处 ， 甚 至 有 的 单 位 存 在 维 保 过 程 “ 走 过 场 ” ， 在 同一 年 度 内 连 续 受 到 行 政 处 罚 。 四 、 工 作 要 求 （ 一 ） 落 实 主 体 责 任 ， 提 高 电 梯 维 保 质 量 各 相 关 维 保 单 位 （ 含 A 、 B 、 C 、 D 级 单 位 ） 要 持 续 按 照 企业 质 量 保 证 体 系 要 求 ， 落 实 加 强 人 员 培 训 教 育 、 内 部 工 作 质量 检 查 和 现 场 维 保 作 业 质 量 管 理 ， 规 范 操 作 程 序 ， 切 实 提 高电 梯 维 保 质 量 。 对 照 此 次 质 量 信 用 等 级 评 价 中 发 现 的 问 题 ，举 一 反 三 ， 认 真 落 实 整 改 ， 及 时 将 完 成 整 改 闭 环 材 料 （ 含 书面 整 改 报 告 、 见 证 材 料 加 盖 单 位 公 章 ） 扫 描 上 传 至 9 6 1 9 6 平台 。 其 中 被 评 为 C 级 的 电 梯 维 保 单 位 应 在 此 通 知 下 发 之 日 起1 个 月 内 完 成 整 改 ， 并 将 书 面 报 告 报 送 市 、 县 两 级 市 场 监 管局 ， 逾 期 未 提 交 书 面 整 改 报 告 或 整 改 不 合 格 的 ， 将 关 停 监 管平 台 账 号 并 暂 停 新 增 业 务 ， 直 至 整 改 合 格 。 被 评 为 D 级 的 电梯 维 保 单 位 应 在 2 个 月 内 完 成 问 题 整 改 ， 并 将 书 面 报 告 报 送市 、 县 两 级 市 场 监 管 局 ， 逾 期 未 整 改 到 位 的 ， 依 照 相 关 法 律法 规 严 肃 处 理 ， 暂 停 动 态 监 管 平 台 上 的 账 号 和 受 理 新 增 业 务 ，直 至 整 改 复 查 合 格 。 （ 二 ） 加 强 技 术 把 关 ， 提 升 电 梯 安 全 运 行 水 平 省 特 检 院 龙 岩 分 院 以 及 各 电 梯 检 测 单 位 要 充 分 发 挥 检验 检 测 机 构 技 术 优 势 ， 持 续 做 好 电 梯 安 全 技 术 把 关 。 要 严 格按 照 安 全 技 术 规 范 以 及 相 关 要 求 开 展 电 梯 定 期 检 验 检 测 、 维保质 量 与 运 行 质 量 监 督 抽 查 等 工 作 ， 并 加 强 结 果 统 计 和 分 析 。在 检 验 、 监 督 抽 查 中 发 现 事 故 隐 患 ， 要 及 时 按 相 关 要 求 和 程序 进 行 报 告 和 处 理 。 （ 三 ） 实 施 差 异 化 监 管 ， 压 实 企 业 安 全 主 体 责 任 各 县 级 市 场 监 管 局 要 按 照 属 地 监 管 原 则 ， 跟 踪 落 实 对 辖区 内 维 保 单 位 问 题 整 改 ， 各 县 级 局 要 督 促 辖 区 维 保 单 位 （ 含外 地 驻 点 分 支 机 构 ） 在 要 求 期 限 内 落 实 问 题 整 改 。 市 局 负 责开 展 对 所 有 维 保 单 位 1 次 年 度 综 合 检 查 ， 按 照 《 办 法 》 要 求按 照 其 信 用 等 级 结 果 实 施 差 异 化 分 类 监 管 ， 制 定 全 市 2 0 2 6年 对 B 、 C 、 D 级 单 位 的 监 督 检 查 计 划 ， 由 县 级 局 负 责 具 体 工作 落 实 。 即 2 0 2 6 年 底 前 分 别 对 B 级 维 保 单 位 安 排 1 次 监 督 检查 ， 对 C 级 单 位 安 排 不 少 于 2 次 监 督 检 查 ， D 级 维 保 单 位 分别 安 排 不 少 于 3 次 监 督 检 查 。 五 、 其 他 本 次 信 用 评 价 结 果 ， 是 对 维 保 单 位 本 年 度 电 梯 维 护 保 养质 量 安 全 保 障 能 力 的 综 合 体 现 ， 可 作 为 电 梯 使 用 单 位 择 优 选择 维 保 服 务 的 重 要 参 考 ， 也 是 监 管 部 门 开 展 分 类 监 管 、 风 险预 警 提 示 的 核 心 依 据 。 等 级 评 价 结 果 通 报 将 向 社 会 公 示 ， 同时 抄 送 市 安 办 、 市 城 市 管 理 、 市 公 共 资 源 交 易 中 心 等 相 关 部门 。 各 维 保 单 位 应 及 时 将 本 单 位 的 等 级 评 价 结 果 如 实 填 写 在电 梯 信 息 公 示 栏 ， 接 受 社 会 监 督 。 各 级 市 场 监 管 部 门 、 省 特检 院 龙 岩 分 院 、 市 电 梯 行 业 协 会 要 积 极 采 用 评 价 结 果 推 动 社会公 众 参 与 电 梯 安 全 监 督 ， 以 公 正 监 管 促 进 公 平 竞 争 、 优 胜 劣 汰 ， 确 保 我 市 电 梯 安 全 持 续 保 持 平 稳 态 势 。 素材来源：龙岩市市场监督管理局
A498: 0496 | B498: 政府行政令|事故与安全|维保 | C498: 闽梯圈 | D498: 福州市市场监管局部署2026年电梯安全重点工作 | E498: http://mp.weixin.qq.com/s?__biz=Mzg2Mjc1NDA3OQ==&mid=2247493003&idx=1&sn=0513f32c9fceeac86bf44f4ebe59a096 | F498: 2026-03-17 11:38:20 | G498: 为切实加强电梯安全监管，扎实做好年初复工复产与全国两会期间安全保障工作，3月5日，市市场监管局召开全市电梯维保工作会议。 会议通报 全市电梯安全状况，重点梳理电梯维保质量、应急救援、公众诉求处置、物联网平台应用、舆情应对等工作薄弱环节，紧盯维保不规范、应急响应不及时、群众诉求办理质效等突出问题，明确整改方向与提升路径。同时，会议还分析了当前行业发展和安全监管形势，系统部署了2026年重点工作任务。 会议强调 电梯安全事关民生福祉与社会稳定，全市市场监管系统与各电梯维保单位要提高政治站位，强化底线思维，把保障人民群众乘梯安全放在首位。要紧扣复工复产安全生产关键节点，聚焦全国两会期间安全保障重大任务，以最严标准、最实举措、最硬作风，全面排查化解电梯安全风险隐患，坚决守牢安全底线，为经济社会平稳运行提供坚实安全保障。 会议要求 01 压实主体责任，规范维保行为 要严格按照安全技术规范开展维保作业，落实“日管控、周排查、月调度”机制，严禁虚假维保、超期维保等行为，确保维保过程可追溯、质量可管控。 02 聚焦重点领域，强化隐患整治 要紧盯商场、医院、交通枢纽、老旧小区等人员密集场所与重点区域电梯，建立隐患台账、实行闭环管理，做到隐患早发现、早处置、早清零。 03 提升应急能力，强化值班值守 要完善电梯应急救援预案，严格落实24小时值班制度，提升96196应急救援的响应速度，确保突发情况快速响应、高效处置。 04 严格监管执法，筑牢安全防线 各监管部门要加大监督检查与执法力度，严厉打击违法违规行为，强化维保单位信用监管，推动形成规范有序、优胜劣汰的市场环境，持续提升全市电梯安全运行水平。 下一步 市市场监管局将持续强化日常监管，深化电梯智慧监管应用，同时加强宣传和信用体系建设，以不断提升电梯安全保障能力，切实守护好人民群众“上下出行”的安全防线。 市局党组成员、四级调研员陈存伟及省特检院郑强副院长出席会议，市局特安处、各县（市）区市场监管部门、省特检院有关部门、电梯维保单位等相关负责人参加会议。 素材来源：福州市市场监督管理局特安处
A499: 0497 | B499: 政府行政令 | C499: 闽梯圈 | D499: 福建住建：公布全省物业主管部门群众举报电话及邮箱 | E499: http://mp.weixin.qq.com/s?__biz=Mzg2Mjc1NDA3OQ==&mid=2247493004&idx=1&sn=0246518fe7f5e02d14e4f4794bb760a4 | F499: 2026-03-18 10:34:27 | G499: 为做好治理物业服务 突出问题“投诉举报”有关工作 省住建厅现向社会公布 各设区市、县（市、区）物业主管部门 投诉举报电话及邮箱 素材来源：福建住建
A500: 0498 | B500: 政策与法规 | C500: 闽梯圈 | D500: 干货___公司销售电梯并提供安装，安装费收入增值税是多少？ | E500: http://mp.weixin.qq.com/s?__biz=Mzg2Mjc1NDA3OQ==&mid=2247493005&idx=1&sn=ab49d72c12bf5666e1c11ed403184585 | F500: 2026-03-19 11:22:51 | G500: 请问： 公司销售电梯并提供安装，安装费收入增值税是多少？答复： 13%。 从今年开始，一项应税交易，既有销售电梯又有安装，要统一按主要业务销售电梯13% 征收增值税，不再存在安装可以适用简易计税的问题。参考： 财政部税务总局公告2026年第13号： 三、关于一项应税交易涉及两个以上税率一般纳税人发生下列情形，应当按照应税交易的主要业务适用税率： （一）销售软件产品的同时提供的软件安装、维护、培训等服务，适用软件产品的税率。 （二）销售活动板房、机器设备、钢结构件等货物的同时提供的安装服务，适用货物的税率。 （三）充换电业务中销售电力产品的同时收取的蓄电池更换、定位、维护等服务费，适用电力产品的税率。 （四）提供交通工具租赁服务的同时收取的信息技术等服务费，适用租赁服务的税率。 纳税人发生的与本条上述情形类似的应税交易，比照执行。
A501: 0499 | B501: 政府行政令|地方政策与补助 | C501: 闽梯圈 | D501: 转载丨福建省政府办公厅印发重要实施意见 | E501: http://mp.weixin.qq.com/s?__biz=Mzg2Mjc1NDA3OQ==&mid=2247493006&idx=1&sn=7b7335e5b86cb011a0b339feb2eabc90 | F501: 2026-03-20 10:59:46 | G501: 福建省人民政府办公厅关于印发 《福建省城市更新工作实施意见》的通知 闽政办〔2026〕3号 各市、县（区）人民政府，平潭综合实验区管委会，省人民政府各部门、各直属机构，各大企业，各高等院校： 《福建省城市更新工作实施意见》已经省委和省政府研究同意，现印发给你们，请认真组织实施。 福建省人民政府办公厅 2026年1月27日 （此件主动公开） 福建省城市更新工作实施意见 为深入贯彻落实党的二十大和二十届历次全会以及中央城市工作会议精神，坚持以人民为中心，以建设创新、宜居、美丽、韧性、文明、智慧的现代化人民城市为目标，大力实施城市更新行动，提出本实施意见。 一、重点任务 以满足人民日益增长的美好生活需要为根本目的，以城市更新为重要抓手，坚持扩大内需，坚持惠民生和促消费、投资于物和投资于人紧密结合，以新需求引领新供给，以新供给创造新需求，着力解决老旧小区、老旧社区、城中村居住环境质量不高、功能短板突出、长效管理机制不健全，以及老旧街区、老旧厂区空间利用低效、活力不足、城市文化遗产闲置等问题，力争到2030年，城市生活空间品质、公共服务水平及社区治理能力持续提升，老城区发展新动能不断释放，城市生态系统得到有效修复，房屋安全性能、基础设施智慧化水平显著提升，城市更加安全、更具韧性，民生福祉切实增强，逐步形成具有福建特色的可持续城市更新模式。 （一）加强既有建筑改造利用。全面动态掌握房屋建筑安全隐患底数，推进棚户区、城市危旧房、低效建筑改造与存量房屋改造利用，严禁以危险住房名义违法违规拆除改造保护对象。开展人员密集场所公共建筑安全隐患专项排查整治。实施城镇预制板房屋治理改造行动和地震易发区房屋设施加固工程。推进既有建筑节能降碳改造。指导福州、厦门开展房屋体检、保险等试点。鼓励有条件的城市积极开展数字家庭建设。到2027年，完成已纳入国家计划项目的棚户区改造安置房竣工交付。 （二）推进城镇老旧小区整治改造。统筹开展城镇老旧小区整治，全力消除安全隐患，整治小区及周边环境，支持有条件的楼栋加装电梯。加强老旧小区改造质量安全监管，结合改造同步完善小区长效管理机制。到2030年，老旧小区居住品质显著提升，政府引导、市场运作、居民参与的整治改造与长效治理机制更加完善。 （三）高标准开展完整社区建设。引导新建社区落实完整社区建设要求，推动既有社区结合社区体检补齐社区功能短板，构建城市一刻钟便民生活圈。支持有条件的社区开展智慧社区建设。引导居民、规划师、设计师等参与社区建设。2026-2028年每年打造一批省级完整社区建设项目。 （四）推进老旧街区、城中村等更新改造。改造提升商业步行街和旧商业街区，推进老旧火车站及周边街区统筹实施更新改造试点工作。因地制宜实施城中村改造，支持通过购买存量住房筹集安置住房。稳妥推进历史遗留停工项目的分类化解与处置。2026-2027年按照成熟一批、实施一批的原则，滚动推进城中村改造。到2030年，每个设区市每年至少打造一条特色街区。 （五）推动都市产业增容提质。优化提升传统产业，培育壮大新兴产业和未来产业，促进服务业优质高效发展。基于生态、产业等资源禀赋进行差异化城市更新，支持各地结合低效用地再开发工作，保护生产空间、优化产业布局，推动都市产业智能化、绿色化、融合化发展。加快发展人工智能、数据等技术密集型产业。鼓励对布局、环保和生产要素具有较高要求的制造业向开发区、工业园区集聚发展。大力发展生产性服务业，推动先进制造业与现代服务业融合发展。到2030年，持续推动都市产业增容提质，进一步提升产城人融合水平，不断激发城市发展新动能。 （六）完善城市功能。加强普惠性、基础性、兜底性民生建设。充分利用存量闲置房屋和低效用地，完善城市教育、医疗、托育、养老、文化、体育等公共服务设施。因地制宜建设改造群众身边的全民健身场地设施。推动消费基础设施改造升级。积极稳妥推进“平急两用”公共基础设施建设，福州、厦门、泉州加快打造一批具有隔离功能的旅游居住设施。开展城市无障碍设施体检，推进无障碍设施改造提升。按照职住平衡、租购并举推进保障性住房发展。2026—2028年每年打造一批无障碍设施改造提升片区。到2030年，全面实现义务教育优质均衡发展，常住人口超过300万的设区市均设置二级以上老年医院或康复医院，新增筹集建设保障性住房2万套。 （七）加强城市基础设施建设改造。推进地下空间统筹开发和综合利用、城市地下管线管网和综合管廊建设改造。推动城市供水设施提标改造、城市生活污水管网全覆盖。推广福州市城区水系联排联调机制，加快实施城市排水防涝能力提升工程。持续开展电力系统供电水平提升改造。推进城市燃气安全专项整治。深入推进生活垃圾分类、建筑垃圾资源化利用。加强公共消防设施、防灾工程建设。完善城市交通基础设施，推进福州、厦门第三轮轨道交通建设。优化城市货运网络规划设计。推进新型城市基础设施建设，加快老旧市政基础设施智能化改造、城市基础设施生命线安全工程建设。到2027年，基本消除城市建成区生活污水直排口和设施空白区。到2030年，全省生活垃圾资源化利用率达85%，建筑垃圾资源化利用率达50%以上。 （八）修复城市生态系统。加快修复受损山体、城市湿地，实施城镇周边林相改善，筑牢生态安全屏障。有序推进漳州、三明国家级海绵示范城市建设。持续深入推进污染防治攻坚，巩固城市黑臭水体治理成效，推进城市水土保持和生态清洁小流域建设。加强建设用地土壤污染风险管控和修复。持续推进城市绿环绿廊绿楔绿道建设和公共绿地开放共享，开展城市小微公共空间改造，增加一批社区公园、口袋公园。推广装配式建造方式，开展装配式装修试点。加快推进可再生能源建筑应用。到2030年，城市建成区可渗透地面面积比例达到45%。 （九）保护传承城市历史文化。推进第四次全国文物普查，开展老城区和老街区等城市文化遗产资源调查。支持厦门、泰宁、建瓯、宁德等申报国家历史文化名城，支持具备条件的市（县）申报省级历史文化名城。加快全省名城街区保护规划的编制与审批。建立健全保护前置机制，不随意拆除具有保护价值的老建筑、古民居。建立以居民为主体的保护实施机制，加强传统建筑工匠培训。保护具有重要历史文化价值的地名，稳妥清理不规范地名。实施城市文物遗产强基工程。加强城市更新重点地区与地段风貌管控。推进老旧厂房厂区功能转换，提升工业遗产活化利用水平。到2030年，每年实施一批历史文化街区（传统街巷）改善提升项目，实现历史文化街区保护规划编制率达到100%。 二、实施路径 （一）开展城市体检评估。推动市级及以上城市和部分县级市开展城市体检，鼓励因地制宜开展专项体检、片区体检、社区体检。2027年底前，推动县级市全面开展城市体检。 （二）完善城市更新规划实施体系。推动各地建立完善“城市更新专项规划—城市片区策划—项目实施方案”的规划实施体系，编制城市更新专项规划和年度实施计划。 （三）编制城市设计方案。开展城市更新重点地段城市设计，明确不同尺度的设计管控要求，并纳入城市更新地块建设改造的设计条件。严格管理超大体量公共建筑、超高层建筑。 （四）打造省级城市更新项目。每年打造一批省级城市更新项目，范围涵盖城市片区更新、完整社区建设、福道、无障碍设施及绿色建筑建设改造、城镇污水提质增效等重点领域，省级财政予以支持。统筹用好各级各部门财政资金，鼓励符合条件的工程项目实施工程总承包模式，探索城市建设公益性项目与经营性项目综合开发、统筹运营、分别核算，积极吸引社会资本参与，保障资金来源，确保建设质量。 （五）建立可持续城市更新模式。健全完善房屋市政设施全生命周期运维与安全管理体系，依法对大龄房屋组织实施安全鉴定，全面排查城市基础设施风险隐患，推广厂网一体专业化运行维护管理模式与地下管廊有偿使用管理机制，优化生活垃圾处理特许经营机制，完善建设运维长效管理制度。健全完善城市运行管理服务平台功能和机制，大力发展“人工智能+”城市治理，拓展人工智能在城市基础设施、公共服务设施、房屋建筑等运行、维护、管理的应用，常态化开展户外广告排查整治、窨井盖治理、人行道净化等专项行动。完善住宅专项维修资金政策，推动建立房屋安全管理公共资金筹集、管理、使用模式。完善社会治理体系，因地制宜探索“连片共管”管理模式，健全社区服务设施运营机制。推广“城管进社区”工作和“721工作法”，提升城市管理、服务、执法质效。实行重大决策社会稳定风险评估，规范化建设综治中心。 三、支撑保障 （一）健全多元化投融资方式。积极争取中央资金，鼓励各地积极争取超长期特别国债、中央预算内投资、中央财政专项、新型政策性金融工具等各类资金支持城市更新项目建设。支持有条件的城市申报全国城市更新行动示范城市，推动谋划历史文化街区保护提升项目纳入国家项目储备库。加大地方财政投入，各级各部门统筹安排相关资金支持城市更新工作，合力保障城市更新有力有序有效实施。城市体检和城市更新专项规划编制费用应纳入财政预算。对符合法律、行政法规或国务院规定条件的保障性住房建设等城市更新项目，支持申报地方政府专项债券需求。支持将专项债券资金用作城市更新项目资本金。允许地方政府专项债券用于土地储备。推动银行信贷支持。在不新增政府隐性债务的情况下，鼓励政策性银行、商业银行在依法合规、风险可控、商业可持续的前提下，积极参与城市更新，强化长周期信贷支持。引导社会资本参与，鼓励采取资产证券化（ABS）、不动产投资信托基金（REITs）、投资人+EPC等多元化融资模式，保障可经营、可出售、可出租的城市更新项目。推动持有型不动产ABS试点，支持发行公司债券用于城市更新。鼓励民营企业以直接投资、独资、控股或参股等方式参与基础设施和公共事业特许经营。支持房屋产权单位或居民自主出资实施更新。 （二）完善规划用地政策。支持土地复合利用，完善用途转换过渡期政策，明确用途转换和兼容使用的正面清单、负面清单和管控要求，妥善处理不动产登记历史遗留问题，推动土地混合开发利用和用途依法合理转换。在符合国土空间规划，保障公共利益和安全、符合更新目标的前提下，鼓励各地通过土地用途兼容、建筑功能混合等方式，补齐公共服务设施、基础设施、公共安全设施短板。持续盘活利用低效用地，支持利用存量低效用地建设保障性住房、发展产业、完善公共服务设施，对收购已建成商品房或收回收购土地用于配售型保障性住房的，将土地使用权取得方式调整为划拨，鼓励各地优化完善地价计收规则。鼓励低效用地再开发试点城市探索完善闲置土地使用权收回机制，优化零星用地集中改造、容积率转移或奖励政策。统筹建筑规模，在符合更新规划单元规划要求的前提下，更新实施单元规划的建筑量可在更新规划单元内统筹布局、精准投放，鼓励探索规划建筑量跨更新规划单元进行统筹及异地等价值转移的政策和机制。完善不动产登记制度，聚焦用途功能和空间协调，适应城市更新不同情形，加强不动产登记与规划实施衔接，优化存量用地和低效用地的产权归集、整合、置换和登记政策。 （三）优化审批许可制度。提高审批效率，统筹新增与存量建设用地，涉及国土空间规划调整的依法办理。支持各地结合工程建设项目审批制度改革，探索优化存量更新改造项目的审批管理程序和措施。建立豁免清单，在保障安全、公共利益及周边权益的前提下，可针对微更新项目及符合条件的市政设施更新项目，探索制定建设工程规划许可豁免清单并完善监管机制。 （四）落实税费优惠政策。符合法律、行政法规或国务院规定条件的城市公共基础设施项目的投资经营所得，享受企业所得税“三免三减半”。对棚户区改造安置住房建设用地，依法依规免征城镇土地使用税。棚户区改造项目免征各项行政事业性收费和政府性基金。 （五）健全法规标准体系。推进各设区市城市更新相关立法工作。鼓励各地因地制宜完善适用于城市更新的技术标准或导则。大力研发新技术、新工艺、新材料，加快科技成果推广应用。制定支持老旧住房自主更新、原拆原建的政策措施。 四、组织实施 省级建立城市更新工作协调机制，由省住建厅牵头，适时召开联席会议。构建市级统筹、部门联动、分级落实的工作格局，及时解决项目推进过程中实际问题。强化区县组织实施责任落实，推动各区县党委和政府发挥牵头抓总作用。加强社区人民调解组织队伍建设，充分发挥街道社区作用，调动人民群众参与城市更新积极性。建立专家委员会制度，积极引入台湾团队参与城市更新，探索闽台合作路径。不断完善适应城市更新的工程项目建设实施管理制度。省、市城市更新工作相关部门应加大对成效显著的地区、项目的支持力度，及时总结、推广典型经验，组织开展现场观摩与学习培训，做好宣传引导工作，营造良好的舆论氛围。 本实施意见自公布之日起施行，有效期至2030年。 素材来源：福建省人民政府官网
A502: 0500 | B502: 其他 | C502: 雷登电梯GOTS | D502: 爱心工程！情牵边疆教育事_捐资助学显担当 | E502: http://mp.weixin.qq.com/s?__biz=MzIzMjE2ODY3Ng==&mid=2649643027&idx=1&sn=439ec18f1a33d90a0bd173fc1b26d365 | F502: 2026-03-20 09:30:01 | G502: 在祖国的西北边陲，新疆和田地区洛浦县的土地上，教育的火种正等待着更多的温暖与滋养。洛浦县第二小学，一所承载着当地无数家庭希望的学校，却因资金有限，在改善教学条件、助力学生成长的道路上步履维艰。雷登电梯，作为一家始终将社会责任镌刻在企业发展基因中的行业先锋，在了解到学校的困境后，毅然伸出援手，以现金捐赠的方式，为洛浦县第二小学的教育发展注入了强劲动力，用实际行动践行着“取之于社会，用之于社会”的企业担当。 教育是民族振兴、社会进步的基石，是提高国民素质、促进人的全面发展的根本途径。雷登电梯深知，偏远地区的教育发展，不仅关系到当地孩子的未来，更关系到整个地区的长远发展。当得知洛浦县第二小学由于经费紧张，无法为学生更新教学设备、改善学习环境，甚至部分贫困学生面临着学习用品短缺的困境时，雷登电梯的领导班子迅速召开专题会议，决定启动“爱心助学”计划，向学校捐赠用于学校的基础设施建设、教学设备购置以及贫困学生的帮扶工作。 “我们不能让地域的偏远成为孩子们追逐梦想的阻碍，不能让资金的短缺熄灭孩子们对知识的渴望。”雷登电梯董事长在捐赠仪式上动情地说道，“雷登电梯的发展离不开社会的支持，如今我们有能力了，就应该尽自己的一份力量，为教育事业添砖加瓦，为孩子们的未来保驾护航。” 雷登电梯的现金捐赠行动，不仅为洛浦县第二小学的教育发展带来了实实在在的改变，也在社会上引起了强烈反响。社会各界纷纷为雷登电梯的善举点赞，许多企业和个人也受到启发，积极参与到公益助学的行列中来，形成了一股关爱教育、帮扶贫困学生的强大正能量。 对于雷登电梯而言，这次捐赠行动只是企业履行社会责任的一个缩影。多年来，雷登电梯始终坚持“以人为本，关爱社会”的企业理念，积极参与各类公益事业。无论是在抗震救灾的一线，还是在扶贫攻坚的战场，无论是在教育助学的道路上，还是在环保公益的行动中，都能看到雷登电梯的身影。企业通过捐款捐物、志愿服务、产业帮扶等多种方式，为社会的发展和进步贡献着自己的力量。

Sheet 公众号清单
A1: 序号 | B1: 公众号名称 | C1: 公众号性质 | D1: 添加日期 | E1: （本周）文章数量
A2: 1 | B2: FUJITEC富士达电梯 | C2: 电梯企业 | D2: 45646 | E2: =COUNTIF(文章清单!C:C,B2) -> 0
A3: 2 | B3: SJEC江南嘉捷电梯 | C3: 电梯企业 | D3: 45646 | E3: =COUNTIF(文章清单!C:C,B3) -> 0
A4: 3 | B4: 爱佳梯电梯物联网平台 | C4: 公司 | D4: 45646 | E4: =COUNTIF(文章清单!C:C,B4) -> 0
A5: 4 | B5: 奥的斯电梯 | C5: 电梯企业 | D5: 45646 | E5: =COUNTIF(文章清单!C:C,B5) -> 0
A6: 5 | B6: 迪斯卡电梯 | C6: 电梯企业 | D6: 45646 | E6: =COUNTIF(文章清单!C:C,B6) -> 0
A7: 6 | B7: 蒂升电梯 | C7: 电梯企业 | D7: 45646 | E7: =COUNTIF(文章清单!C:C,B7) -> 0
A8: 7 | B8: 点梯智云 | C8: 公司 | D8: 45646 | E8: =COUNTIF(文章清单!C:C,B8) -> 0
A9: 8 | B9: 电梯 | C9: 个人 | D9: 45646 | E9: =COUNTIF(文章清单!C:C,B9) -> 0
A10: 9 | B10: 电梯安全论坛 | C10: 个人 | D10: 45646 | E10: =COUNTIF(文章清单!C:C,B10) -> 0
A11: 10 | B11: 电梯帮 | C11: 个人 | D11: 45646 | E11: =COUNTIF(文章清单!C:C,B11) -> 0
A12: 11 | B12: 电梯标准与检验 | C12: 个人 | D12: 45646 | E12: =COUNTIF(文章清单!C:C,B12) -> 0
A13: 12 | B13: 电梯部 | C13: 个人 | D13: 45646 | E13: =COUNTIF(文章清单!C:C,B13) -> 0
... A140: 139 | B140: 智慧电梯圈 | C140: 制造企业 | D140: 45651 | E140: =COUNTIF(文章清单!C:C,B140) -> 0

Sheet 类别清单
A1: 类别名称 | B1: 添加日期 | C1: （本周）文章数量
A2: 安装 | B2: 45646 | C2: =COUNTIF(文章清单!B:B,"*"&A2&"*") -> 0
A3: 维保 | B3: 45646 | C3: =COUNTIF(文章清单!B:B,"*"&A3&"*") -> 0
A4: 法规 | B4: 45646 | C4: =COUNTIF(文章清单!B:B,"*"&A4&"*") -> 0
A5: 政府行政令 | B5: 45646 | C5: =COUNTIF(文章清单!B:B,"*"&A5&"*") -> 0
A6: 惩罚 | B6: 45646 | C6: =COUNTIF(文章清单!B:B,"*"&A6&"*") -> 0
A7: 事故 | B7: 45646 | C7: =COUNTIF(文章清单!B:B,"*"&A7&"*") -> 0
A8: 曳引机 | B8: 45663 | C8: =COUNTIF(文章清单!B:B,"*"&A8&"*") -> 0
A9: 制动器 | B9: 45663 | C9: =COUNTIF(文章清单!B:B,"*"&A9&"*") -> 0
A10: 广告 | B10: 45665 | C10: =COUNTIF(文章清单!B:B,"*"&A10&"*") -> 0
A11: 祝福 | B11: 45665 | C11: =COUNTIF(文章清单!B:B,"*"&A11&"*") -> 0
A12: 其他 | B12: 45646 | C12: =COUNTIF(文章清单!B:B,"*"&A12&"*") -> 0
